<?xml version="1.0" encoding="UTF-8"?>
<!DOCTYPE cesAna SYSTEM "xcesAnaIPI.dtd">
<cesAna xmlns:xlink="http://www.w3.org/1999/xlink" version="1.0" type="lex disamb">
<chunkList>
 <chunk id="ch1">
  <chunk type="s">
   <tok>
    <orth>Gdzie</orth>
    <lex disamb="1"><base>gdzie</base><ctag>adv</ctag></lex>
   </tok>
   <tok>
    <orth>znajdę</orth>
    <lex disamb="1"><base>znajść</base><ctag>fin:sg:pri:perf</ctag></lex>
    <lex disamb="1"><base>znaleźć</base><ctag>fin:sg:pri:perf</ctag></lex>
   </tok>
   <tok>
    <orth>informacje</orth>
    <lex disamb="1"><base>informacja</base><ctag>subst:pl:acc:f</ctag></lex>
   </tok>
   <tok>
    <orth>o</orth>
    <lex disamb="1"><base>o</base><ctag>prep:loc</ctag></lex>
   </tok>
   <tok>
    <orth>wysokości</orth>
    <lex disamb="1"><base>wysokość</base><ctag>subst:sg:loc:f</ctag></lex>
   </tok>
   <tok>
    <orth>mienia</orth>
    <lex disamb="1"><base>mienie</base><ctag>subst:sg:gen:n</ctag></lex>
   </tok>
   <tok>
    <orth>Skarbu</orth>
    <lex disamb="1"><base>skarb</base><ctag>subst:sg:gen:m3</ctag></lex>
   </tok>
   <tok>
    <orth>Państwa</orth>
    <lex disamb="1"><base>państwo</base><ctag>subst:sg:gen:n</ctag></lex>
   </tok>
   <ns/>
   <tok>
    <orth>?</orth>
    <lex disamb="1"><base>?</base><ctag>interp</ctag></lex>
   </tok>
  </chunk>
  <chunk type="s">
   <tok>
    <orth>Gdzie</orth>
    <lex disamb="1"><base>gdzie</base><ctag>adv</ctag></lex>
   </tok>
   <tok>
    <orth>urodził</orth>
    <lex disamb="1"><base>urodzić</base><ctag>praet:sg:m1:perf</ctag></lex>
   </tok>
   <tok>
    <orth>się</orth>
    <lex disamb="1"><base>się</base><ctag>qub</ctag></lex>
   </tok>
   <tok>
    <orth>Mariusz</orth>
    <lex disamb="1"><base>Mariusz</base><ctag>subst:sg:nom:m1</ctag></lex>
   </tok>
   <tok>
    <orth>Pudzianowski</orth>
    <lex disamb="1"><base>pudzianowski</base><ctag>subst:sg:nom:m1</ctag></lex>
   </tok>
   <ns/>
   <tok>
    <orth>?</orth>
    <lex disamb="1"><base>?</base><ctag>interp</ctag></lex>
   </tok>
  </chunk>
  <chunk type="s">
   <tok>
    <orth>Gdzie</orth>
    <lex disamb="1"><base>gdzie</base><ctag>adv</ctag></lex>
   </tok>
   <tok>
    <orth>urodził</orth>
    <lex disamb="1"><base>urodzić</base><ctag>praet:sg:m1:perf</ctag></lex>
   </tok>
   <tok>
    <orth>się</orth>
    <lex disamb="1"><base>się</base><ctag>qub</ctag></lex>
   </tok>
   <tok>
    <orth>Zbigniew</orth>
    <lex disamb="1"><base>Zbigniew</base><ctag>subst:sg:nom:m1</ctag></lex>
   </tok>
   <tok>
    <orth>Boniek</orth>
    <lex disamb="1"><base>Boniek</base><ctag>subst:sg:nom:m1</ctag></lex>
   </tok>
   <ns/>
   <tok>
    <orth>?</orth>
    <lex disamb="1"><base>?</base><ctag>interp</ctag></lex>
   </tok>
  </chunk>
  <chunk type="s">
   <tok>
    <orth>Gdzie</orth>
    <lex disamb="1"><base>gdzie</base><ctag>adv</ctag></lex>
   </tok>
   <tok>
    <orth>walczył</orth>
    <lex disamb="1"><base>walczyć</base><ctag>praet:sg:m1:imperf</ctag></lex>
   </tok>
   <tok>
    <orth>Adamek</orth>
    <lex disamb="1"><base>adamek</base><ctag>subst:sg:nom:m1</ctag></lex>
   </tok>
   <ns/>
   <tok>
    <orth>?</orth>
    <lex disamb="1"><base>?</base><ctag>interp</ctag></lex>
   </tok>
  </chunk>
  <chunk type="s">
   <tok>
    <orth>Gdzie</orth>
    <lex disamb="1"><base>gdzie</base><ctag>adv</ctag></lex>
   </tok>
   <tok>
    <orth>zginął</orth>
    <lex disamb="1"><base>zginąć</base><ctag>praet:sg:m1:perf</ctag></lex>
   </tok>
   <tok>
    <orth>Rysiek</orth>
    <lex disamb="1"><base>Rysiek</base><ctag>subst:sg:nom:m1</ctag></lex>
   </tok>
   <tok>
    <orth>z</orth>
    <lex disamb="1"><base>z</base><ctag>prep:gen:nwok</ctag></lex>
   </tok>
   <tok>
    <orth>&quot;</orth>
    <lex disamb="1"><base>&quot;</base><ctag>interp</ctag></lex>
   </tok>
   <ns/>
   <tok>
    <orth>Klanu</orth>
    <lex disamb="1"><base>klan</base><ctag>subst:sg:gen:m3</ctag></lex>
   </tok>
   <ns/>
   <tok>
    <orth>&quot;</orth>
    <lex disamb="1"><base>&quot;</base><ctag>interp</ctag></lex>
   </tok>
   <ns/>
   <tok>
    <orth>?</orth>
    <lex disamb="1"><base>?</base><ctag>interp</ctag></lex>
   </tok>
  </chunk>
  <chunk type="s">
   <tok>
    <orth>Gdzie</orth>
    <lex disamb="1"><base>gdzie</base><ctag>adv</ctag></lex>
   </tok>
   <tok>
    <orth>znajduje</orth>
    <lex disamb="1"><base>znajdować</base><ctag>fin:sg:ter:imperf</ctag></lex>
    <lex disamb="1"><base>znajdywać</base><ctag>fin:sg:ter:imperf</ctag></lex>
   </tok>
   <tok>
    <orth>się</orth>
    <lex disamb="1"><base>się</base><ctag>qub</ctag></lex>
   </tok>
   <tok>
    <orth>najszybszy</orth>
    <lex disamb="1"><base>szybki</base><ctag>adj:sg:nom:m3:sup</ctag></lex>
   </tok>
   <tok>
    <orth>komputer</orth>
    <lex disamb="1"><base>komputer</base><ctag>subst:sg:nom:m3</ctag></lex>
   </tok>
   <ns/>
   <tok>
    <orth>?</orth>
    <lex disamb="1"><base>?</base><ctag>interp</ctag></lex>
   </tok>
  </chunk>
  <chunk type="s">
   <tok>
    <orth>Gdzie</orth>
    <lex disamb="1"><base>gdzie</base><ctag>adv</ctag></lex>
   </tok>
   <tok>
    <orth>umarł</orth>
    <lex disamb="1"><base>umrzeć</base><ctag>praet:sg:m1:perf</ctag></lex>
   </tok>
   <tok>
    <orth>Rysiek</orth>
    <lex disamb="1"><base>Rysiek</base><ctag>subst:sg:nom:m1</ctag></lex>
   </tok>
   <tok>
    <orth>z</orth>
    <lex disamb="1"><base>z</base><ctag>prep:gen:nwok</ctag></lex>
   </tok>
   <tok>
    <orth>&quot;</orth>
    <lex disamb="1"><base>&quot;</base><ctag>interp</ctag></lex>
   </tok>
   <ns/>
   <tok>
    <orth>Klanu</orth>
    <lex disamb="1"><base>klan</base><ctag>subst:sg:gen:m3</ctag></lex>
   </tok>
   <ns/>
   <tok>
    <orth>&quot;</orth>
    <lex disamb="1"><base>&quot;</base><ctag>interp</ctag></lex>
   </tok>
   <ns/>
   <tok>
    <orth>?</orth>
    <lex disamb="1"><base>?</base><ctag>interp</ctag></lex>
   </tok>
  </chunk>
  <chunk type="s">
   <tok>
    <orth>Gdzie</orth>
    <lex disamb="1"><base>gdzie</base><ctag>adv</ctag></lex>
   </tok>
   <tok>
    <orth>urodził</orth>
    <lex disamb="1"><base>urodzić</base><ctag>praet:sg:m1:perf</ctag></lex>
   </tok>
   <tok>
    <orth>się</orth>
    <lex disamb="1"><base>się</base><ctag>qub</ctag></lex>
   </tok>
   <tok>
    <orth>Chopin</orth>
    <lex disamb="1"><base>Chopin</base><ctag>subst:sg:nom:m1</ctag></lex>
   </tok>
   <ns/>
   <tok>
    <orth>?</orth>
    <lex disamb="1"><base>?</base><ctag>interp</ctag></lex>
   </tok>
  </chunk>
  <chunk type="s">
   <tok>
    <orth>Gdzie</orth>
    <lex disamb="1"><base>gdzie</base><ctag>adv</ctag></lex>
   </tok>
   <tok>
    <orth>rosną</orth>
    <lex disamb="1"><base>rosnąć</base><ctag>fin:pl:ter:imperf</ctag></lex>
   </tok>
   <tok>
    <orth>banany</orth>
    <lex disamb="1"><base>banan</base><ctag>subst:pl:nom:m2</ctag></lex>
   </tok>
   <ns/>
   <tok>
    <orth>?</orth>
    <lex disamb="1"><base>?</base><ctag>interp</ctag></lex>
   </tok>
  </chunk>
  <chunk type="s">
   <tok>
    <orth>Gdzie</orth>
    <lex disamb="1"><base>gdzie</base><ctag>adv</ctag></lex>
   </tok>
   <tok>
    <orth>są</orth>
    <lex disamb="1"><base>być</base><ctag>fin:pl:ter:imperf</ctag></lex>
   </tok>
   <tok>
    <orth>Plewiska</orth>
    <lex disamb="1"><base>plewiska</base><ctag>subst:pl:nom:f</ctag></lex>
   </tok>
   <ns/>
   <tok>
    <orth>?</orth>
    <lex disamb="1"><base>?</base><ctag>interp</ctag></lex>
   </tok>
  </chunk>
  <chunk type="s">
   <tok>
    <orth>Gdzie</orth>
    <lex disamb="1"><base>gdzie</base><ctag>adv</ctag></lex>
   </tok>
   <tok>
    <orth>znajduje</orth>
    <lex disamb="1"><base>znajdować</base><ctag>fin:sg:ter:imperf</ctag></lex>
    <lex disamb="1"><base>znajdywać</base><ctag>fin:sg:ter:imperf</ctag></lex>
   </tok>
   <tok>
    <orth>się</orth>
    <lex disamb="1"><base>się</base><ctag>qub</ctag></lex>
   </tok>
   <tok>
    <orth>UAM</orth>
    <lex disamb="1"><base>UAM</base><ctag>subst:sg:nom:m3</ctag></lex>
   </tok>
   <ns/>
   <tok>
    <orth>?</orth>
    <lex disamb="1"><base>?</base><ctag>interp</ctag></lex>
   </tok>
  </chunk>
  <chunk type="s">
   <tok>
    <orth>Gdzie</orth>
    <lex disamb="1"><base>gdzie</base><ctag>adv</ctag></lex>
   </tok>
   <tok>
    <orth>znajdują</orth>
    <lex disamb="1"><base>znajdować</base><ctag>fin:pl:ter:imperf</ctag></lex>
    <lex disamb="1"><base>znajdywać</base><ctag>fin:pl:ter:imperf</ctag></lex>
   </tok>
   <tok>
    <orth>się</orth>
    <lex disamb="1"><base>się</base><ctag>qub</ctag></lex>
   </tok>
   <tok>
    <orth>Plewiska</orth>
    <lex disamb="1"><base>plewiska</base><ctag>subst:sg:nom:f</ctag></lex>
   </tok>
   <ns/>
   <tok>
    <orth>?</orth>
    <lex disamb="1"><base>?</base><ctag>interp</ctag></lex>
   </tok>
  </chunk>
  <chunk type="s">
   <tok>
    <orth>Gdzie</orth>
    <lex disamb="1"><base>gdzie</base><ctag>adv</ctag></lex>
   </tok>
   <tok>
    <orth>Autocad</orth>
    <lex disamb="1"><base>autocad</base><ctag>subst:sg:nom:m1</ctag></lex>
   </tok>
   <tok>
    <orth>zapisuje</orth>
    <lex disamb="1"><base>zapisywać</base><ctag>fin:sg:ter:imperf</ctag></lex>
   </tok>
   <tok>
    <orth>kopie</orth>
    <lex disamb="1"><base>kopia</base><ctag>subst:pl:acc:f</ctag></lex>
   </tok>
   <tok>
    <orth>zapasowe</orth>
    <lex disamb="1"><base>zapasowy</base><ctag>adj:pl:acc:f:pos</ctag></lex>
   </tok>
   <ns/>
   <tok>
    <orth>?</orth>
    <lex disamb="1"><base>?</base><ctag>interp</ctag></lex>
   </tok>
  </chunk>
  <chunk type="s">
   <tok>
    <orth>Gdzie</orth>
    <lex disamb="1"><base>gdzie</base><ctag>adv</ctag></lex>
   </tok>
   <tok>
    <orth>powstały</orth>
    <lex disamb="1"><base>powstać</base><ctag>praet:pl:m3:perf</ctag></lex>
   </tok>
   <tok>
    <orth>Legiony</orth>
    <lex disamb="1"><base>legion</base><ctag>subst:pl:nom:m3</ctag></lex>
   </tok>
   <tok>
    <orth>Polskie</orth>
    <lex disamb="1"><base>polski</base><ctag>adj:pl:nom:m3:pos</ctag></lex>
   </tok>
   <ns/>
   <tok>
    <orth>?</orth>
    <lex disamb="1"><base>?</base><ctag>interp</ctag></lex>
   </tok>
  </chunk>
  <chunk type="s">
   <tok>
    <orth>Gdzie</orth>
    <lex disamb="1"><base>gdzie</base><ctag>adv</ctag></lex>
   </tok>
   <tok>
    <orth>jest</orth>
    <lex disamb="1"><base>być</base><ctag>fin:sg:ter:imperf</ctag></lex>
   </tok>
   <tok>
    <orth>Ambasada</orth>
    <lex disamb="1"><base>ambasada</base><ctag>subst:sg:nom:f</ctag></lex>
   </tok>
   <tok>
    <orth>Japonii</orth>
    <lex disamb="1"><base>Japonia</base><ctag>subst:sg:gen:f</ctag></lex>
   </tok>
   <ns/>
   <tok>
    <orth>?</orth>
    <lex disamb="1"><base>?</base><ctag>interp</ctag></lex>
   </tok>
  </chunk>
  <chunk type="s">
   <tok>
    <orth>Gdzie</orth>
    <lex disamb="1"><base>gdzie</base><ctag>adv</ctag></lex>
   </tok>
   <tok>
    <orth>wykryto</orth>
    <lex disamb="1"><base>wykryć</base><ctag>imps:perf</ctag></lex>
   </tok>
   <tok>
    <orth>w</orth>
    <lex disamb="1"><base>w</base><ctag>prep:loc:nwok</ctag></lex>
   </tok>
   <tok>
    <orth>Polsce</orth>
    <lex disamb="1"><base>Polska</base><ctag>subst:sg:loc:f</ctag></lex>
   </tok>
   <tok>
    <orth>wirusa</orth>
    <lex disamb="1"><base>wirus</base><ctag>subst:sg:gen:m2</ctag></lex>
   </tok>
   <tok>
    <orth>grypy</orth>
    <lex disamb="1"><base>grypa</base><ctag>subst:sg:gen:f</ctag></lex>
   </tok>
   <ns/>
   <tok>
    <orth>?</orth>
    <lex disamb="1"><base>?</base><ctag>interp</ctag></lex>
   </tok>
  </chunk>
  <chunk type="s">
   <tok>
    <orth>Gdzie</orth>
    <lex disamb="1"><base>gdzie</base><ctag>adv</ctag></lex>
   </tok>
   <tok>
    <orth>ulokować</orth>
    <lex disamb="1"><base>ulokować</base><ctag>inf:perf</ctag></lex>
   </tok>
   <tok>
    <orth>pieniądze</orth>
    <lex disamb="1"><base>pieniądz</base><ctag>subst:pl:acc:m3</ctag></lex>
   </tok>
   <ns/>
   <tok>
    <orth>?</orth>
    <lex disamb="1"><base>?</base><ctag>interp</ctag></lex>
   </tok>
  </chunk>
  <chunk type="s">
   <tok>
    <orth>Gdzie</orth>
    <lex disamb="1"><base>gdzie</base><ctag>adv</ctag></lex>
   </tok>
   <tok>
    <orth>urodził</orth>
    <lex disamb="1"><base>urodzić</base><ctag>praet:sg:m1:perf</ctag></lex>
   </tok>
   <tok>
    <orth>się</orth>
    <lex disamb="1"><base>się</base><ctag>qub</ctag></lex>
   </tok>
   <tok>
    <orth>Zbigniew</orth>
    <lex disamb="1"><base>Zbigniew</base><ctag>subst:sg:nom:m1</ctag></lex>
   </tok>
   <tok>
    <orth>Herbert</orth>
    <lex disamb="1"><base>Herbert</base><ctag>subst:sg:nom:m1</ctag></lex>
   </tok>
   <ns/>
   <tok>
    <orth>?</orth>
    <lex disamb="1"><base>?</base><ctag>interp</ctag></lex>
   </tok>
  </chunk>
  <chunk type="s">
   <tok>
    <orth>Gdzie</orth>
    <lex disamb="1"><base>gdzie</base><ctag>adv</ctag></lex>
   </tok>
   <tok>
    <orth>uchwalono</orth>
    <lex disamb="1"><base>uchwalić</base><ctag>imps:perf</ctag></lex>
   </tok>
   <tok>
    <orth>Konstytucje</orth>
    <lex disamb="1"><base>konstytucja</base><ctag>subst:pl:acc:f</ctag></lex>
   </tok>
   <tok>
    <orth>3</orth>
    <lex disamb="1"><base>3</base><ctag>adj:sg:gen:m3:pos</ctag></lex>
   </tok>
   <tok>
    <orth>maja</orth>
    <lex disamb="1"><base>maj</base><ctag>subst:sg:gen:m3</ctag></lex>
   </tok>
   <ns/>
   <tok>
    <orth>?</orth>
    <lex disamb="1"><base>?</base><ctag>interp</ctag></lex>
   </tok>
  </chunk>
  <chunk type="s">
   <tok>
    <orth>Gdzie</orth>
    <lex disamb="1"><base>gdzie</base><ctag>adv</ctag></lex>
   </tok>
   <tok>
    <orth>umieścić</orth>
    <lex disamb="1"><base>umieścić</base><ctag>inf:perf</ctag></lex>
   </tok>
   <tok>
    <orth>czujnik</orth>
    <lex disamb="1"><base>czujnik</base><ctag>subst:sg:acc:m3</ctag></lex>
   </tok>
   <tok>
    <orth>czadu</orth>
    <lex disamb="1"><base>Czad</base><ctag>subst:sg:gen:m3</ctag></lex>
    <lex disamb="1"><base>czad</base><ctag>subst:sg:gen:m3</ctag></lex>
   </tok>
   <ns/>
   <tok>
    <orth>?</orth>
    <lex disamb="1"><base>?</base><ctag>interp</ctag></lex>
   </tok>
  </chunk>
  <chunk type="s">
   <tok>
    <orth>Gdzie</orth>
    <lex disamb="1"><base>gdzie</base><ctag>adv</ctag></lex>
   </tok>
   <tok>
    <orth>występuje</orth>
    <lex disamb="1"><base>występować</base><ctag>fin:sg:ter:imperf</ctag></lex>
   </tok>
   <tok>
    <orth>witamina</orth>
    <lex disamb="1"><base>witamina</base><ctag>subst:sg:nom:f</ctag></lex>
   </tok>
   <tok>
    <orth>D</orth>
    <lex disamb="1"><base>D</base><ctag>brev:pun</ctag></lex>
    <lex disamb="1"><base>dawny</base><ctag>brev:pun</ctag></lex>
    <lex disamb="1"><base>dom</base><ctag>brev:pun</ctag></lex>
    <lex disamb="1"><base>dzień</base><ctag>brev:pun</ctag></lex>
   </tok>
   <ns/>
   <tok>
    <orth>?</orth>
    <lex disamb="1"><base>?</base><ctag>interp</ctag></lex>
   </tok>
  </chunk>
  <chunk type="s">
   <tok>
    <orth>Gdzie</orth>
    <lex disamb="1"><base>gdzie</base><ctag>adv</ctag></lex>
   </tok>
   <tok>
    <orth>wyrobić</orth>
    <lex disamb="1"><base>wyrobić</base><ctag>inf:perf</ctag></lex>
   </tok>
   <tok>
    <orth>paszport</orth>
    <lex disamb="1"><base>paszport</base><ctag>subst:sg:acc:m3</ctag></lex>
   </tok>
   <ns/>
   <tok>
    <orth>?</orth>
    <lex disamb="1"><base>?</base><ctag>interp</ctag></lex>
   </tok>
  </chunk>
  <chunk type="s">
   <tok>
    <orth>Gdzie</orth>
    <lex disamb="1"><base>gdzie</base><ctag>adv</ctag></lex>
   </tok>
   <tok>
    <orth>pada</orth>
    <lex disamb="1"><base>padać</base><ctag>fin:sg:ter:imperf</ctag></lex>
   </tok>
   <tok>
    <orth>śnieg</orth>
    <lex disamb="1"><base>śnieg</base><ctag>subst:sg:nom:m3</ctag></lex>
   </tok>
   <ns/>
   <tok>
    <orth>?</orth>
    <lex disamb="1"><base>?</base><ctag>interp</ctag></lex>
   </tok>
  </chunk>
  <chunk type="s">
   <tok>
    <orth>Gdzie</orth>
    <lex disamb="1"><base>gdzie</base><ctag>adv</ctag></lex>
   </tok>
   <tok>
    <orth>pada</orth>
    <lex disamb="1"><base>padać</base><ctag>fin:sg:ter:imperf</ctag></lex>
   </tok>
   <tok>
    <orth>śnieg</orth>
    <lex disamb="1"><base>śnieg</base><ctag>subst:sg:nom:m3</ctag></lex>
   </tok>
   <ns/>
   <tok>
    <orth>?</orth>
    <lex disamb="1"><base>?</base><ctag>interp</ctag></lex>
   </tok>
  </chunk>
  <chunk type="s">
   <tok>
    <orth>Gdzie</orth>
    <lex disamb="1"><base>gdzie</base><ctag>adv</ctag></lex>
   </tok>
   <tok>
    <orth>wyrobić</orth>
    <lex disamb="1"><base>wyrobić</base><ctag>inf:perf</ctag></lex>
   </tok>
   <tok>
    <orth>paszport</orth>
    <lex disamb="1"><base>paszport</base><ctag>subst:sg:acc:m3</ctag></lex>
   </tok>
   <ns/>
   <tok>
    <orth>?</orth>
    <lex disamb="1"><base>?</base><ctag>interp</ctag></lex>
   </tok>
  </chunk>
  <chunk type="s">
   <tok>
    <orth>Gdzie</orth>
    <lex disamb="1"><base>gdzie</base><ctag>adv</ctag></lex>
   </tok>
   <tok>
    <orth>występuje</orth>
    <lex disamb="1"><base>występować</base><ctag>fin:sg:ter:imperf</ctag></lex>
   </tok>
   <tok>
    <orth>witamina</orth>
    <lex disamb="1"><base>witamina</base><ctag>subst:sg:nom:f</ctag></lex>
   </tok>
   <tok>
    <orth>D</orth>
    <lex disamb="1"><base>D</base><ctag>brev:pun</ctag></lex>
    <lex disamb="1"><base>dawny</base><ctag>brev:pun</ctag></lex>
    <lex disamb="1"><base>dom</base><ctag>brev:pun</ctag></lex>
    <lex disamb="1"><base>dzień</base><ctag>brev:pun</ctag></lex>
   </tok>
   <ns/>
   <tok>
    <orth>?</orth>
    <lex disamb="1"><base>?</base><ctag>interp</ctag></lex>
   </tok>
  </chunk>
  <chunk type="s">
   <tok>
    <orth>Gdzie</orth>
    <lex disamb="1"><base>gdzie</base><ctag>adv</ctag></lex>
   </tok>
   <tok>
    <orth>umieścić</orth>
    <lex disamb="1"><base>umieścić</base><ctag>inf:perf</ctag></lex>
   </tok>
   <tok>
    <orth>czujnik</orth>
    <lex disamb="1"><base>czujnik</base><ctag>subst:sg:acc:m3</ctag></lex>
   </tok>
   <tok>
    <orth>czadu</orth>
    <lex disamb="1"><base>Czad</base><ctag>subst:sg:gen:m3</ctag></lex>
    <lex disamb="1"><base>czad</base><ctag>subst:sg:gen:m3</ctag></lex>
   </tok>
   <ns/>
   <tok>
    <orth>?</orth>
    <lex disamb="1"><base>?</base><ctag>interp</ctag></lex>
   </tok>
  </chunk>
  <chunk type="s">
   <tok>
    <orth>Gdzie</orth>
    <lex disamb="1"><base>gdzie</base><ctag>adv</ctag></lex>
   </tok>
   <tok>
    <orth>uchwalono</orth>
    <lex disamb="1"><base>uchwalić</base><ctag>imps:perf</ctag></lex>
   </tok>
   <tok>
    <orth>Konstytucje</orth>
    <lex disamb="1"><base>konstytucja</base><ctag>subst:pl:acc:f</ctag></lex>
   </tok>
   <tok>
    <orth>3</orth>
    <lex disamb="1"><base>3</base><ctag>adj:sg:gen:m3:pos</ctag></lex>
   </tok>
   <tok>
    <orth>maja</orth>
    <lex disamb="1"><base>maj</base><ctag>subst:sg:gen:m3</ctag></lex>
   </tok>
   <ns/>
   <tok>
    <orth>?</orth>
    <lex disamb="1"><base>?</base><ctag>interp</ctag></lex>
   </tok>
  </chunk>
  <chunk type="s">
   <tok>
    <orth>Gdzie</orth>
    <lex disamb="1"><base>gdzie</base><ctag>adv</ctag></lex>
   </tok>
   <tok>
    <orth>urodził</orth>
    <lex disamb="1"><base>urodzić</base><ctag>praet:sg:m1:perf</ctag></lex>
   </tok>
   <tok>
    <orth>się</orth>
    <lex disamb="1"><base>się</base><ctag>qub</ctag></lex>
   </tok>
   <tok>
    <orth>Zbigniew</orth>
    <lex disamb="1"><base>Zbigniew</base><ctag>subst:sg:nom:m1</ctag></lex>
   </tok>
   <tok>
    <orth>Herbert</orth>
    <lex disamb="1"><base>Herbert</base><ctag>subst:sg:nom:m1</ctag></lex>
   </tok>
   <ns/>
   <tok>
    <orth>?</orth>
    <lex disamb="1"><base>?</base><ctag>interp</ctag></lex>
   </tok>
  </chunk>
  <chunk type="s">
   <tok>
    <orth>Gdzie</orth>
    <lex disamb="1"><base>gdzie</base><ctag>adv</ctag></lex>
   </tok>
   <tok>
    <orth>mieszka</orth>
    <lex disamb="1"><base>mieszkać</base><ctag>fin:sg:ter:imperf</ctag></lex>
   </tok>
   <tok>
    <orth>Selena</orth>
    <lex disamb="1"><base>selena</base><ctag>subst:sg:nom:f</ctag></lex>
   </tok>
   <tok>
    <orth>Gomez</orth>
    <lex disamb="1"><base>gomez</base><ctag>subst:sg:nom:f</ctag></lex>
   </tok>
   <ns/>
   <tok>
    <orth>?</orth>
    <lex disamb="1"><base>?</base><ctag>interp</ctag></lex>
   </tok>
  </chunk>
  <chunk type="s">
   <tok>
    <orth>Gdzie</orth>
    <lex disamb="1"><base>gdzie</base><ctag>adv</ctag></lex>
   </tok>
   <tok>
    <orth>ulokować</orth>
    <lex disamb="1"><base>ulokować</base><ctag>inf:perf</ctag></lex>
   </tok>
   <tok>
    <orth>pieniądze</orth>
    <lex disamb="1"><base>pieniądz</base><ctag>subst:pl:acc:m3</ctag></lex>
   </tok>
   <ns/>
   <tok>
    <orth>?</orth>
    <lex disamb="1"><base>?</base><ctag>interp</ctag></lex>
   </tok>
  </chunk>
  <chunk type="s">
   <tok>
    <orth>Gdzie</orth>
    <lex disamb="1"><base>gdzie</base><ctag>adv</ctag></lex>
   </tok>
   <tok>
    <orth>oglądać</orth>
    <lex disamb="1"><base>oglądać</base><ctag>inf:imperf</ctag></lex>
   </tok>
   <tok>
    <orth>stream</orth>
    <lex disamb="1"><base>stream</base><ctag>subst:pl:acc:m2</ctag></lex>
   </tok>
   <tok>
    <orth>line</orth>
    <lex disamb="1"><base>line</base><ctag>subst:pl:acc:m2</ctag></lex>
   </tok>
   <tok>
    <orth>movies</orth>
    <lex disamb="1"><base>movies</base><ctag>subst:pl:acc:m2</ctag></lex>
   </tok>
   <tok>
    <orth>za</orth>
    <lex disamb="1"><base>za</base><ctag>prep:acc</ctag></lex>
   </tok>
   <tok>
    <orth>darmo</orth>
    <lex disamb="1"><base>darmo</base><ctag>adv</ctag></lex>
   </tok>
   <ns/>
   <tok>
    <orth>?</orth>
    <lex disamb="1"><base>?</base><ctag>interp</ctag></lex>
   </tok>
  </chunk>
  <chunk type="s">
   <tok>
    <orth>Gdzie</orth>
    <lex disamb="1"><base>gdzie</base><ctag>adv</ctag></lex>
   </tok>
   <tok>
    <orth>najlepiej</orth>
    <lex disamb="1"><base>dobrze</base><ctag>adv:sup</ctag></lex>
   </tok>
   <tok>
    <orth>mieszkać</orth>
    <lex disamb="1"><base>mieszkać</base><ctag>inf:imperf</ctag></lex>
   </tok>
   <tok>
    <orth>w</orth>
    <lex disamb="1"><base>w</base><ctag>prep:loc:nwok</ctag></lex>
   </tok>
   <tok>
    <orth>Polsce</orth>
    <lex disamb="1"><base>Polska</base><ctag>subst:sg:loc:f</ctag></lex>
   </tok>
   <ns/>
   <tok>
    <orth>?</orth>
    <lex disamb="1"><base>?</base><ctag>interp</ctag></lex>
   </tok>
  </chunk>
  <chunk type="s">
   <tok>
    <orth>Gdzie</orth>
    <lex disamb="1"><base>gdzie</base><ctag>adv</ctag></lex>
   </tok>
   <tok>
    <orth>znajdę</orth>
    <lex disamb="1"><base>znajść</base><ctag>fin:sg:pri:perf</ctag></lex>
    <lex disamb="1"><base>znaleźć</base><ctag>fin:sg:pri:perf</ctag></lex>
   </tok>
   <tok>
    <orth>informacje</orth>
    <lex disamb="1"><base>informacja</base><ctag>subst:pl:acc:f</ctag></lex>
   </tok>
   <tok>
    <orth>nt</orth>
    <lex disamb="1"><base>na temat</base><ctag>brev:pun</ctag></lex>
   </tok>
   <ns/>
   <tok>
    <orth>.</orth>
    <lex disamb="1"><base>.</base><ctag>interp</ctag></lex>
   </tok>
   <tok>
    <orth>poprawności</orth>
    <lex disamb="1"><base>poprawność</base><ctag>subst:sg:gen:f</ctag></lex>
   </tok>
   <tok>
    <orth>wykonania</orth>
    <lex disamb="1"><base>wykonać</base><ctag>ger:sg:gen:n:perf:aff</ctag></lex>
   </tok>
   <tok>
    <orth>budżetu</orth>
    <lex disamb="1"><base>budżet</base><ctag>subst:sg:gen:m3</ctag></lex>
   </tok>
   <ns/>
   <tok>
    <orth>?</orth>
    <lex disamb="1"><base>?</base><ctag>interp</ctag></lex>
   </tok>
  </chunk>
  <chunk type="s">
   <tok>
    <orth>Gdzie</orth>
    <lex disamb="1"><base>gdzie</base><ctag>adv</ctag></lex>
   </tok>
   <tok>
    <orth>znajdę</orth>
    <lex disamb="1"><base>znajść</base><ctag>fin:sg:pri:perf</ctag></lex>
    <lex disamb="1"><base>znaleźć</base><ctag>fin:sg:pri:perf</ctag></lex>
   </tok>
   <tok>
    <orth>informacje</orth>
    <lex disamb="1"><base>informacja</base><ctag>subst:pl:acc:f</ctag></lex>
   </tok>
   <tok>
    <orth>o</orth>
    <lex disamb="1"><base>o</base><ctag>prep:loc</ctag></lex>
   </tok>
   <tok>
    <orth>wysokości</orth>
    <lex disamb="1"><base>wysokość</base><ctag>subst:sg:loc:f</ctag></lex>
   </tok>
   <tok>
    <orth>długu</orth>
    <lex disamb="1"><base>dług</base><ctag>subst:sg:gen:m3</ctag></lex>
   </tok>
   <tok>
    <orth>publicznego</orth>
    <lex disamb="1"><base>publiczny</base><ctag>adj:sg:gen:m3:pos</ctag></lex>
   </tok>
   <ns/>
   <tok>
    <orth>?</orth>
    <lex disamb="1"><base>?</base><ctag>interp</ctag></lex>
   </tok>
  </chunk>
  <chunk type="s">
   <tok>
    <orth>Gdzie</orth>
    <lex disamb="1"><base>gdzie</base><ctag>adv</ctag></lex>
   </tok>
   <tok>
    <orth>powstały</orth>
    <lex disamb="1"><base>powstać</base><ctag>praet:pl:m3:perf</ctag></lex>
   </tok>
   <tok>
    <orth>Legiony</orth>
    <lex disamb="1"><base>legion</base><ctag>subst:pl:nom:m3</ctag></lex>
   </tok>
   <tok>
    <orth>Polskie</orth>
    <lex disamb="1"><base>polski</base><ctag>adj:pl:nom:m3:pos</ctag></lex>
   </tok>
   <ns/>
   <tok>
    <orth>?</orth>
    <lex disamb="1"><base>?</base><ctag>interp</ctag></lex>
   </tok>
  </chunk>
  <chunk type="s">
   <tok>
    <orth>Gdzie</orth>
    <lex disamb="1"><base>gdzie</base><ctag>adv</ctag></lex>
   </tok>
   <tok>
    <orth>Autocad</orth>
    <lex disamb="1"><base>autocad</base><ctag>subst:sg:nom:m1</ctag></lex>
   </tok>
   <tok>
    <orth>zapisuje</orth>
    <lex disamb="1"><base>zapisywać</base><ctag>fin:sg:ter:imperf</ctag></lex>
   </tok>
   <tok>
    <orth>kopie</orth>
    <lex disamb="1"><base>kopia</base><ctag>subst:pl:acc:f</ctag></lex>
   </tok>
   <tok>
    <orth>zapasowe</orth>
    <lex disamb="1"><base>zapasowy</base><ctag>adj:pl:acc:f:pos</ctag></lex>
   </tok>
   <ns/>
   <tok>
    <orth>?</orth>
    <lex disamb="1"><base>?</base><ctag>interp</ctag></lex>
   </tok>
  </chunk>
  <chunk type="s">
   <tok>
    <orth>Gdzie</orth>
    <lex disamb="1"><base>gdzie</base><ctag>adv</ctag></lex>
   </tok>
   <tok>
    <orth>w</orth>
    <lex disamb="1"><base>w</base><ctag>prep:loc:nwok</ctag></lex>
   </tok>
   <tok>
    <orth>Krakowie</orth>
    <lex disamb="1"><base>Kraków</base><ctag>subst:sg:loc:m3</ctag></lex>
   </tok>
   <tok>
    <orth>znajduje</orth>
    <lex disamb="1"><base>znajdować</base><ctag>fin:sg:ter:imperf</ctag></lex>
    <lex disamb="1"><base>znajdywać</base><ctag>fin:sg:ter:imperf</ctag></lex>
   </tok>
   <tok>
    <orth>się</orth>
    <lex disamb="1"><base>się</base><ctag>qub</ctag></lex>
   </tok>
   <tok>
    <orth>sklep</orth>
    <lex disamb="1"><base>sklep</base><ctag>subst:sg:nom:m3</ctag></lex>
   </tok>
   <tok>
    <orth>New</orth>
    <lex disamb="1"><base>Newa</base><ctag>subst:pl:gen:f</ctag></lex>
   </tok>
   <tok>
    <orth>Yorker</orth>
    <lex disamb="1"><base>yorker</base><ctag>subst:sg:gen:f</ctag></lex>
   </tok>
   <ns/>
   <tok>
    <orth>?</orth>
    <lex disamb="1"><base>?</base><ctag>interp</ctag></lex>
   </tok>
  </chunk>
  <chunk type="s">
   <tok>
    <orth>Gdzie</orth>
    <lex disamb="1"><base>gdzie</base><ctag>adv</ctag></lex>
   </tok>
   <tok>
    <orth>jest</orth>
    <lex disamb="1"><base>być</base><ctag>fin:sg:ter:imperf</ctag></lex>
   </tok>
   <tok>
    <orth>Tusk</orth>
    <lex disamb="1"><base>Tusk</base><ctag>subst:sg:nom:m1</ctag></lex>
   </tok>
   <ns/>
   <tok>
    <orth>?</orth>
    <lex disamb="1"><base>?</base><ctag>interp</ctag></lex>
   </tok>
  </chunk>
  <chunk type="s">
   <tok>
    <orth>Gdzie</orth>
    <lex disamb="1"><base>gdzie</base><ctag>adv</ctag></lex>
   </tok>
   <tok>
    <orth>jest</orth>
    <lex disamb="1"><base>być</base><ctag>fin:sg:ter:imperf</ctag></lex>
   </tok>
   <tok>
    <orth>Donald</orth>
    <lex disamb="1"><base>Donald</base><ctag>subst:sg:nom:m1</ctag></lex>
   </tok>
   <tok>
    <orth>Tusk</orth>
    <lex disamb="1"><base>Tusk</base><ctag>subst:sg:nom:m1</ctag></lex>
   </tok>
   <ns/>
   <tok>
    <orth>?</orth>
    <lex disamb="1"><base>?</base><ctag>interp</ctag></lex>
   </tok>
  </chunk>
  <chunk type="s">
   <tok>
    <orth>Gdzie</orth>
    <lex disamb="1"><base>gdzie</base><ctag>adv</ctag></lex>
   </tok>
   <tok>
    <orth>jest</orth>
    <lex disamb="1"><base>być</base><ctag>fin:sg:ter:imperf</ctag></lex>
   </tok>
   <tok>
    <orth>Kubica</orth>
    <lex disamb="1"><base>Kubica</base><ctag>subst:sg:nom:m1</ctag></lex>
   </tok>
   <ns/>
   <tok>
    <orth>?</orth>
    <lex disamb="1"><base>?</base><ctag>interp</ctag></lex>
   </tok>
  </chunk>
  <chunk type="s">
   <tok>
    <orth>Gdzie</orth>
    <lex disamb="1"><base>gdzie</base><ctag>adv</ctag></lex>
   </tok>
   <tok>
    <orth>zderzyły</orth>
    <lex disamb="1"><base>zderzyć</base><ctag>praet:pl:m3:perf</ctag></lex>
   </tok>
   <tok>
    <orth>się</orth>
    <lex disamb="1"><base>się</base><ctag>qub</ctag></lex>
   </tok>
   <tok>
    <orth>pociągi</orth>
    <lex disamb="1"><base>pociąg</base><ctag>subst:pl:nom:m3</ctag></lex>
   </tok>
   <ns/>
   <tok>
    <orth>?</orth>
    <lex disamb="1"><base>?</base><ctag>interp</ctag></lex>
   </tok>
  </chunk>
  <chunk type="s">
   <tok>
    <orth>Gdzie</orth>
    <lex disamb="1"><base>gdzie</base><ctag>adv</ctag></lex>
   </tok>
   <tok>
    <orth>kupić</orth>
    <lex disamb="1"><base>kupić</base><ctag>inf:perf</ctag></lex>
   </tok>
   <tok>
    <orth>tani</orth>
    <lex disamb="1"><base>tani</base><ctag>adj:sg:acc:m3:pos</ctag></lex>
   </tok>
   <tok>
    <orth>duży</orth>
    <lex disamb="1"><base>duży</base><ctag>adj:sg:acc:m3:pos</ctag></lex>
   </tok>
   <tok>
    <orth>karton</orth>
    <lex disamb="1"><base>karton</base><ctag>subst:sg:acc:m3</ctag></lex>
   </tok>
   <tok>
    <orth>ozdobny</orth>
    <lex disamb="1"><base>ozdobny</base><ctag>adj:sg:acc:m3:pos</ctag></lex>
   </tok>
   <ns/>
   <tok>
    <orth>?</orth>
    <lex disamb="1"><base>?</base><ctag>interp</ctag></lex>
   </tok>
  </chunk>
  <chunk type="s">
   <tok>
    <orth>Gdzie</orth>
    <lex disamb="1"><base>gdzie</base><ctag>adv</ctag></lex>
   </tok>
   <tok>
    <orth>Nergal</orth>
    <lex disamb="1"><base>nergal</base><ctag>subst:sg:nom:m1</ctag></lex>
   </tok>
   <tok>
    <orth>będzie</orth>
    <lex disamb="1"><base>być</base><ctag>bedzie:sg:ter:imperf</ctag></lex>
   </tok>
   <tok>
    <orth>jurorem</orth>
    <lex disamb="1"><base>juror</base><ctag>subst:sg:inst:m1</ctag></lex>
   </tok>
   <ns/>
   <tok>
    <orth>?</orth>
    <lex disamb="1"><base>?</base><ctag>interp</ctag></lex>
   </tok>
  </chunk>
  <chunk type="s">
   <tok>
    <orth>Gdzie</orth>
    <lex disamb="1"><base>gdzie</base><ctag>adv</ctag></lex>
   </tok>
   <tok>
    <orth>jest</orth>
    <lex disamb="1"><base>być</base><ctag>fin:sg:ter:imperf</ctag></lex>
   </tok>
   <tok>
    <orth>Olsztyn</orth>
    <lex disamb="1"><base>Olsztyn</base><ctag>subst:sg:nom:m3</ctag></lex>
   </tok>
   <ns/>
   <tok>
    <orth>?</orth>
    <lex disamb="1"><base>?</base><ctag>interp</ctag></lex>
   </tok>
  </chunk>
  <chunk type="s">
   <tok>
    <orth>Gdzie</orth>
    <lex disamb="1"><base>gdzie</base><ctag>adv</ctag></lex>
   </tok>
   <tok>
    <orth>jest</orth>
    <lex disamb="1"><base>być</base><ctag>fin:sg:ter:imperf</ctag></lex>
   </tok>
   <tok>
    <orth>Kościół</orth>
    <lex disamb="1"><base>kościół</base><ctag>subst:sg:nom:m3</ctag></lex>
   </tok>
   <tok>
    <orth>pw</orth>
    <lex disamb="1"><base>PW</base><ctag>subst:sg:nom:f</ctag></lex>
   </tok>
   <tok>
    <orth>św</orth>
    <lex disamb="1"><base>świadek</base><ctag>brev:pun</ctag></lex>
    <lex disamb="1"><base>święty</base><ctag>brev:pun</ctag></lex>
   </tok>
   <tok>
    <orth>Gdzie</orth>
    <lex disamb="1"><base>gdzie</base><ctag>adv</ctag></lex>
   </tok>
   <tok>
    <orth>jest</orth>
    <lex disamb="1"><base>być</base><ctag>fin:sg:ter:imperf</ctag></lex>
   </tok>
   <tok>
    <orth>UAM</orth>
    <lex disamb="1"><base>UAM</base><ctag>subst:sg:nom:m3</ctag></lex>
   </tok>
   <ns/>
   <tok>
    <orth>?</orth>
    <lex disamb="1"><base>?</base><ctag>interp</ctag></lex>
   </tok>
  </chunk>
  <chunk type="s">
   <tok>
    <orth>Gdzie</orth>
    <lex disamb="1"><base>gdzie</base><ctag>adv</ctag></lex>
   </tok>
   <tok>
    <orth>jest</orth>
    <lex disamb="1"><base>być</base><ctag>fin:sg:ter:imperf</ctag></lex>
   </tok>
   <tok>
    <orth>Rondo</orth>
    <lex disamb="1"><base>rondo</base><ctag>subst:sg:nom:n</ctag></lex>
   </tok>
   <tok>
    <orth>Kaponiera</orth>
    <lex disamb="1"><base>kaponiera</base><ctag>subst:sg:nom:f</ctag></lex>
   </tok>
   <ns/>
   <tok>
    <orth>?</orth>
    <lex disamb="1"><base>?</base><ctag>interp</ctag></lex>
   </tok>
  </chunk>
  <chunk type="s">
   <tok>
    <orth>Gdzie</orth>
    <lex disamb="1"><base>gdzie</base><ctag>adv</ctag></lex>
   </tok>
   <tok>
    <orth>jest</orth>
    <lex disamb="1"><base>być</base><ctag>fin:sg:ter:imperf</ctag></lex>
   </tok>
   <tok>
    <orth>Drawa</orth>
    <lex disamb="1"><base>drawa</base><ctag>subst:sg:nom:m1</ctag></lex>
   </tok>
   <ns/>
   <tok>
    <orth>?</orth>
    <lex disamb="1"><base>?</base><ctag>interp</ctag></lex>
   </tok>
  </chunk>
  <chunk type="s">
   <tok>
    <orth>Gdzie</orth>
    <lex disamb="1"><base>gdzie</base><ctag>adv</ctag></lex>
   </tok>
   <tok>
    <orth>jest</orth>
    <lex disamb="1"><base>być</base><ctag>fin:sg:ter:imperf</ctag></lex>
   </tok>
   <tok>
    <orth>Litwa</orth>
    <lex disamb="1"><base>Litwa</base><ctag>subst:sg:nom:f</ctag></lex>
    <lex disamb="1"><base>litwa</base><ctag>subst:sg:nom:f</ctag></lex>
   </tok>
   <ns/>
   <tok>
    <orth>?</orth>
    <lex disamb="1"><base>?</base><ctag>interp</ctag></lex>
   </tok>
  </chunk>
  <chunk type="s">
   <tok>
    <orth>Gdzie</orth>
    <lex disamb="1"><base>gdzie</base><ctag>adv</ctag></lex>
   </tok>
   <tok>
    <orth>leży</orth>
    <lex disamb="1"><base>leżeć</base><ctag>fin:sg:ter:imperf</ctag></lex>
   </tok>
   <tok>
    <orth>Przemyśl</orth>
    <lex disamb="1"><base>Przemyśl</base><ctag>subst:sg:nom:m3</ctag></lex>
   </tok>
   <ns/>
   <tok>
    <orth>?</orth>
    <lex disamb="1"><base>?</base><ctag>interp</ctag></lex>
   </tok>
  </chunk>
  <chunk type="s">
   <tok>
    <orth>Gdzie</orth>
    <lex disamb="1"><base>gdzie</base><ctag>adv</ctag></lex>
   </tok>
   <tok>
    <orth>doda</orth>
    <lex disamb="1"><base>dodać</base><ctag>fin:sg:ter:perf</ctag></lex>
   </tok>
   <tok>
    <orth>mieszka</orth>
    <lex disamb="1"><base>mieszkać</base><ctag>fin:sg:ter:imperf</ctag></lex>
   </tok>
   <ns/>
   <tok>
    <orth>?</orth>
    <lex disamb="1"><base>?</base><ctag>interp</ctag></lex>
   </tok>
  </chunk>
  <chunk type="s">
   <tok>
    <orth>Gdzie</orth>
    <lex disamb="1"><base>gdzie</base><ctag>adv</ctag></lex>
   </tok>
   <tok>
    <orth>mieszka</orth>
    <lex disamb="1"><base>mieszkać</base><ctag>fin:sg:ter:imperf</ctag></lex>
   </tok>
   <tok>
    <orth>Święty</orth>
    <lex disamb="1"><base>święty</base><ctag>adj:sg:nom:m1:pos</ctag></lex>
   </tok>
   <tok>
    <orth>Mikołaj</orth>
    <lex disamb="1"><base>Mikołaj</base><ctag>subst:sg:nom:m1</ctag></lex>
   </tok>
   <ns/>
   <tok>
    <orth>?</orth>
    <lex disamb="1"><base>?</base><ctag>interp</ctag></lex>
   </tok>
  </chunk>
  <chunk type="s">
   <tok>
    <orth>Gdzie</orth>
    <lex disamb="1"><base>gdzie</base><ctag>adv</ctag></lex>
   </tok>
   <tok>
    <orth>można</orth>
    <lex disamb="1"><base>można</base><ctag>pred</ctag></lex>
   </tok>
   <tok>
    <orth>kupić</orth>
    <lex disamb="1"><base>kupić</base><ctag>inf:perf</ctag></lex>
   </tok>
   <tok>
    <orth>ćwieki</orth>
    <lex disamb="1"><base>ćwiek</base><ctag>subst:pl:acc:m3</ctag></lex>
   </tok>
   <ns/>
   <tok>
    <orth>?</orth>
    <lex disamb="1"><base>?</base><ctag>interp</ctag></lex>
   </tok>
  </chunk>
  <chunk type="s">
   <tok>
    <orth>&quot;</orth>
    <lex disamb="1"><base>&quot;</base><ctag>interp</ctag></lex>
   </tok>
   <ns/>
   <tok>
    <orth>Gdzie</orth>
    <lex disamb="1"><base>gdzie</base><ctag>adv</ctag></lex>
   </tok>
   <tok>
    <orth>mogę</orth>
    <lex disamb="1"><base>móc</base><ctag>fin:sg:pri:imperf</ctag></lex>
   </tok>
   <tok>
    <orth>obejrzeć</orth>
    <lex disamb="1"><base>obejrzeć</base><ctag>inf:perf</ctag></lex>
   </tok>
   <tok>
    <orth>&quot;</orth>
    <lex disamb="1"><base>&quot;</base><ctag>interp</ctag></lex>
   </tok>
   <ns/>
   <tok>
    <orth>&quot;</orth>
    <lex disamb="1"><base>&quot;</base><ctag>interp</ctag></lex>
   </tok>
   <ns/>
   <tok>
    <orth>Bejbi</orth>
    <lex disamb="1"><base>bejbi</base><ctag>subst:sg:nom:m3</ctag></lex>
   </tok>
   <tok>
    <orth>Blues</orth>
    <lex disamb="1"><base>blues</base><ctag>subst:sg:nom:m3</ctag></lex>
   </tok>
   <ns/>
   <tok>
    <orth>&quot;</orth>
    <lex disamb="1"><base>&quot;</base><ctag>interp</ctag></lex>
   </tok>
   <ns/>
   <tok>
    <orth>&quot;</orth>
    <lex disamb="1"><base>&quot;</base><ctag>interp</ctag></lex>
   </tok>
   <ns/>
   <tok>
    <orth>?</orth>
    <lex disamb="1"><base>?</base><ctag>interp</ctag></lex>
   </tok>
   <ns/>
   <tok>
    <orth>&quot;</orth>
    <lex disamb="1"><base>&quot;</base><ctag>interp</ctag></lex>
   </tok>
   <tok>
    <orth>Gdzie</orth>
    <lex disamb="1"><base>gdzie</base><ctag>adv</ctag></lex>
   </tok>
   <tok>
    <orth>jest</orth>
    <lex disamb="1"><base>być</base><ctag>fin:sg:ter:imperf</ctag></lex>
   </tok>
   <tok>
    <orth>Piekło</orth>
    <lex disamb="1"><base>piekło</base><ctag>subst:sg:nom:n</ctag></lex>
   </tok>
   <ns/>
   <tok>
    <orth>?</orth>
    <lex disamb="1"><base>?</base><ctag>interp</ctag></lex>
   </tok>
  </chunk>
  <chunk type="s">
   <tok>
    <orth>Gdzie</orth>
    <lex disamb="1"><base>gdzie</base><ctag>adv</ctag></lex>
   </tok>
   <tok>
    <orth>Kasia</orth>
    <lex disamb="1"><base>Kasia</base><ctag>subst:sg:nom:f</ctag></lex>
   </tok>
   <tok>
    <orth>Tusk</orth>
    <lex disamb="1"><base>Tusk</base><ctag>subst:sg:nom:m1</ctag></lex>
   </tok>
   <tok>
    <orth>pozowała</orth>
    <lex disamb="1"><base>pozować</base><ctag>praet:sg:f:imperf</ctag></lex>
   </tok>
   <ns/>
   <tok>
    <orth>?</orth>
    <lex disamb="1"><base>?</base><ctag>interp</ctag></lex>
   </tok>
  </chunk>
  <chunk type="s">
   <tok>
    <orth>Gdzie</orth>
    <lex disamb="1"><base>gdzie</base><ctag>adv</ctag></lex>
   </tok>
   <tok>
    <orth>jest</orth>
    <lex disamb="1"><base>być</base><ctag>fin:sg:ter:imperf</ctag></lex>
   </tok>
   <tok>
    <orth>Bronek</orth>
    <lex disamb="1"><base>Bronek</base><ctag>subst:sg:nom:m1</ctag></lex>
   </tok>
   <ns/>
   <tok>
    <orth>?</orth>
    <lex disamb="1"><base>?</base><ctag>interp</ctag></lex>
   </tok>
  </chunk>
  <chunk type="s">
   <tok>
    <orth>Gdzie</orth>
    <lex disamb="1"><base>gdzie</base><ctag>adv</ctag></lex>
   </tok>
   <tok>
    <orth>jest</orth>
    <lex disamb="1"><base>być</base><ctag>fin:sg:ter:imperf</ctag></lex>
   </tok>
   <tok>
    <orth>Fort</orth>
    <lex disamb="1"><base>fort</base><ctag>subst:sg:nom:m3</ctag></lex>
   </tok>
   <tok>
    <orth>VII</orth>
    <lex disamb="1"><base>vii</base><ctag>subst:sg:nom:m3</ctag></lex>
   </tok>
   <ns/>
   <tok>
    <orth>?</orth>
    <lex disamb="1"><base>?</base><ctag>interp</ctag></lex>
   </tok>
  </chunk>
  <chunk type="s">
   <tok>
    <orth>Gdzie</orth>
    <lex disamb="1"><base>gdzie</base><ctag>adv</ctag></lex>
   </tok>
   <tok>
    <orth>jest</orth>
    <lex disamb="1"><base>być</base><ctag>fin:sg:ter:imperf</ctag></lex>
   </tok>
   <tok>
    <orth>Uniwersytet</orth>
    <lex disamb="1"><base>uniwersytet</base><ctag>subst:sg:nom:m3</ctag></lex>
   </tok>
   <tok>
    <orth>im</orth>
    <lex disamb="1"><base>imienia</base><ctag>brev:pun</ctag></lex>
   </tok>
   <ns/>
   <tok>
    <orth>.</orth>
    <lex disamb="1"><base>.</base><ctag>interp</ctag></lex>
   </tok>
   <tok>
    <orth>Adama</orth>
    <lex disamb="1"><base>Adam</base><ctag>subst:sg:gen:m1</ctag></lex>
   </tok>
   <tok>
    <orth>Mickiewicza</orth>
    <lex disamb="1"><base>Mickiewicz</base><ctag>subst:sg:gen:m1</ctag></lex>
   </tok>
   <ns/>
   <tok>
    <orth>?</orth>
    <lex disamb="1"><base>?</base><ctag>interp</ctag></lex>
   </tok>
  </chunk>
  <chunk type="s">
   <tok>
    <orth>Gdzie</orth>
    <lex disamb="1"><base>gdzie</base><ctag>adv</ctag></lex>
   </tok>
   <tok>
    <orth>jest</orth>
    <lex disamb="1"><base>być</base><ctag>fin:sg:ter:imperf</ctag></lex>
   </tok>
   <tok>
    <orth>Polska</orth>
    <lex disamb="1"><base>Polska</base><ctag>subst:sg:nom:f</ctag></lex>
   </tok>
   <ns/>
   <tok>
    <orth>?</orth>
    <lex disamb="1"><base>?</base><ctag>interp</ctag></lex>
   </tok>
  </chunk>
  <chunk type="s">
   <tok>
    <orth>Gdzie</orth>
    <lex disamb="1"><base>gdzie</base><ctag>adv</ctag></lex>
   </tok>
   <tok>
    <orth>jest</orth>
    <lex disamb="1"><base>być</base><ctag>fin:sg:ter:imperf</ctag></lex>
   </tok>
   <tok>
    <orth>Lizbona</orth>
    <lex disamb="1"><base>Lizbona</base><ctag>subst:sg:nom:f</ctag></lex>
   </tok>
   <ns/>
   <tok>
    <orth>?</orth>
    <lex disamb="1"><base>?</base><ctag>interp</ctag></lex>
   </tok>
  </chunk>
  <chunk type="s">
   <tok>
    <orth>Gdzie</orth>
    <lex disamb="1"><base>gdzie</base><ctag>adv</ctag></lex>
   </tok>
   <tok>
    <orth>jest</orth>
    <lex disamb="1"><base>być</base><ctag>fin:sg:ter:imperf</ctag></lex>
   </tok>
   <tok>
    <orth>krakowskie</orth>
    <lex disamb="1"><base>krakowski</base><ctag>adj:sg:nom:n:pos</ctag></lex>
   </tok>
   <tok>
    <orth>przedmieście</orth>
    <lex disamb="1"><base>przedmieście</base><ctag>subst:sg:nom:n</ctag></lex>
   </tok>
   <ns/>
   <tok>
    <orth>?</orth>
    <lex disamb="1"><base>?</base><ctag>interp</ctag></lex>
   </tok>
  </chunk>
  <chunk type="s">
   <tok>
    <orth>Gdzie</orth>
    <lex disamb="1"><base>gdzie</base><ctag>adv</ctag></lex>
   </tok>
   <tok>
    <orth>jest</orth>
    <lex disamb="1"><base>być</base><ctag>fin:sg:ter:imperf</ctag></lex>
   </tok>
   <tok>
    <orth>Biebrza</orth>
    <lex disamb="1"><base>Biebrza</base><ctag>subst:sg:nom:f</ctag></lex>
   </tok>
   <ns/>
   <tok>
    <orth>?</orth>
    <lex disamb="1"><base>?</base><ctag>interp</ctag></lex>
   </tok>
  </chunk>
  <chunk type="s">
   <tok>
    <orth>Gdzie</orth>
    <lex disamb="1"><base>gdzie</base><ctag>adv</ctag></lex>
   </tok>
   <tok>
    <orth>jest</orth>
    <lex disamb="1"><base>być</base><ctag>fin:sg:ter:imperf</ctag></lex>
   </tok>
   <tok>
    <orth>Liceum</orth>
    <lex disamb="1"><base>liceum</base><ctag>subst:sg:nom:n</ctag></lex>
   </tok>
   <tok>
    <orth>imienia</orth>
    <lex disamb="1"><base>imienie</base><ctag>subst:sg:gen:n</ctag></lex>
    <lex disamb="1"><base>imię</base><ctag>subst:sg:gen:n</ctag></lex>
   </tok>
   <tok>
    <orth>Stanisława</orth>
    <lex disamb="1"><base>Stanisław</base><ctag>subst:sg:gen:m1</ctag></lex>
   </tok>
   <tok>
    <orth>Dubois</orth>
    <lex disamb="1"><base>Dubois</base><ctag>subst:sg:gen:m1</ctag></lex>
   </tok>
   <ns/>
   <tok>
    <orth>?</orth>
    <lex disamb="1"><base>?</base><ctag>interp</ctag></lex>
   </tok>
  </chunk>
  <chunk type="s">
   <tok>
    <orth>Gdzie</orth>
    <lex disamb="1"><base>gdzie</base><ctag>adv</ctag></lex>
   </tok>
   <tok>
    <orth>jest</orth>
    <lex disamb="1"><base>być</base><ctag>fin:sg:ter:imperf</ctag></lex>
   </tok>
   <tok>
    <orth>Kępa</orth>
    <lex disamb="1"><base>Kępa</base><ctag>subst:sg:nom:f</ctag></lex>
    <lex disamb="1"><base>kępa</base><ctag>subst:sg:nom:f</ctag></lex>
   </tok>
   <tok>
    <orth>Oborska</orth>
    <lex disamb="1"><base>oborski</base><ctag>adj:sg:nom:f:pos</ctag></lex>
   </tok>
   <ns/>
   <tok>
    <orth>?</orth>
    <lex disamb="1"><base>?</base><ctag>interp</ctag></lex>
   </tok>
  </chunk>
  <chunk type="s">
   <tok>
    <orth>Gdzie</orth>
    <lex disamb="1"><base>gdzie</base><ctag>adv</ctag></lex>
   </tok>
   <tok>
    <orth>jest</orth>
    <lex disamb="1"><base>być</base><ctag>fin:sg:ter:imperf</ctag></lex>
   </tok>
   <tok>
    <orth>Mokotów</orth>
    <lex disamb="1"><base>Mokotów</base><ctag>subst:sg:nom:m3</ctag></lex>
   </tok>
   <ns/>
   <tok>
    <orth>?</orth>
    <lex disamb="1"><base>?</base><ctag>interp</ctag></lex>
   </tok>
  </chunk>
  <chunk type="s">
   <tok>
    <orth>Gdzie</orth>
    <lex disamb="1"><base>gdzie</base><ctag>adv</ctag></lex>
   </tok>
   <tok>
    <orth>jest</orth>
    <lex disamb="1"><base>być</base><ctag>fin:sg:ter:imperf</ctag></lex>
   </tok>
   <tok>
    <orth>Milanówek</orth>
    <lex disamb="1"><base>Milanówek</base><ctag>subst:sg:nom:m3</ctag></lex>
   </tok>
   <ns/>
   <tok>
    <orth>?</orth>
    <lex disamb="1"><base>?</base><ctag>interp</ctag></lex>
   </tok>
  </chunk>
  <chunk type="s">
   <tok>
    <orth>&quot;</orth>
    <lex disamb="1"><base>&quot;</base><ctag>interp</ctag></lex>
   </tok>
   <ns/>
   <tok>
    <orth>Na</orth>
    <lex disamb="1"><base>na</base><ctag>prep:loc</ctag></lex>
   </tok>
   <tok>
    <orth>jakiej</orth>
    <lex disamb="1"><base>jaki</base><ctag>adj:sg:loc:f:pos</ctag></lex>
   </tok>
   <tok>
    <orth>stronie</orth>
    <lex disamb="1"><base>strona</base><ctag>subst:sg:loc:f</ctag></lex>
   </tok>
   <tok>
    <orth>da</orth>
    <lex disamb="1"><base>dać</base><ctag>fin:sg:ter:perf</ctag></lex>
   </tok>
   <tok>
    <orth>się</orth>
    <lex disamb="1"><base>się</base><ctag>qub</ctag></lex>
   </tok>
   <tok>
    <orth>obejrzeć</orth>
    <lex disamb="1"><base>obejrzeć</base><ctag>inf:perf</ctag></lex>
   </tok>
   <tok>
    <orth>4</orth>
    <lex disamb="1"><base>4</base><ctag>num:pl:nom:m3:congr</ctag></lex>
   </tok>
   <ns/>
   <tok>
    <orth>-</orth>
    <lex disamb="1"><base>-</base><ctag>interp</ctag></lex>
   </tok>
   <ns/>
   <tok>
    <orth>ty</orth>
    <lex disamb="1"><base>ty</base><ctag>ppron12:sg:nom:m1:sec</ctag></lex>
   </tok>
   <tok>
    <orth>sezon</orth>
    <lex disamb="1"><base>sezon</base><ctag>subst:sg:nom:m3</ctag></lex>
   </tok>
   <tok>
    <orth>&quot;</orth>
    <lex disamb="1"><base>&quot;</base><ctag>interp</ctag></lex>
   </tok>
   <ns/>
   <tok>
    <orth>&quot;</orth>
    <lex disamb="1"><base>&quot;</base><ctag>interp</ctag></lex>
   </tok>
   <ns/>
   <tok>
    <orth>Pamiętnika</orth>
    <lex disamb="1"><base>pamiętnik</base><ctag>subst:sg:gen:m3</ctag></lex>
   </tok>
   <tok>
    <orth>Wampirów</orth>
    <lex disamb="1"><base>wampir</base><ctag>subst:pl:gen:m1</ctag></lex>
   </tok>
   <ns/>
   <tok>
    <orth>&quot;</orth>
    <lex disamb="1"><base>&quot;</base><ctag>interp</ctag></lex>
   </tok>
   <ns/>
   <tok>
    <orth>&quot;</orth>
    <lex disamb="1"><base>&quot;</base><ctag>interp</ctag></lex>
   </tok>
   <ns/>
   <tok>
    <orth>?</orth>
    <lex disamb="1"><base>?</base><ctag>interp</ctag></lex>
   </tok>
   <ns/>
   <tok>
    <orth>&quot;</orth>
    <lex disamb="1"><base>&quot;</base><ctag>interp</ctag></lex>
   </tok>
   <tok>
    <orth>Gdzie</orth>
    <lex disamb="1"><base>gdzie</base><ctag>adv</ctag></lex>
   </tok>
   <tok>
    <orth>leży</orth>
    <lex disamb="1"><base>leżeć</base><ctag>fin:sg:ter:imperf</ctag></lex>
   </tok>
   <tok>
    <orth>Ostrołęka</orth>
    <lex disamb="1"><base>Ostrołęka</base><ctag>subst:sg:nom:f</ctag></lex>
    <lex disamb="1"><base>ostrołęka</base><ctag>subst:sg:nom:f</ctag></lex>
   </tok>
   <ns/>
   <tok>
    <orth>?</orth>
    <lex disamb="1"><base>?</base><ctag>interp</ctag></lex>
   </tok>
  </chunk>
  <chunk type="s">
   <tok>
    <orth>Gdzie</orth>
    <lex disamb="1"><base>gdzie</base><ctag>adv</ctag></lex>
   </tok>
   <tok>
    <orth>leży</orth>
    <lex disamb="1"><base>leżeć</base><ctag>fin:sg:ter:imperf</ctag></lex>
   </tok>
   <tok>
    <orth>UAM</orth>
    <lex disamb="1"><base>UAM</base><ctag>subst:sg:nom:m3</ctag></lex>
   </tok>
   <ns/>
   <tok>
    <orth>?</orth>
    <lex disamb="1"><base>?</base><ctag>interp</ctag></lex>
   </tok>
  </chunk>
  <chunk type="s">
   <tok>
    <orth>Gdzie</orth>
    <lex disamb="1"><base>gdzie</base><ctag>adv</ctag></lex>
   </tok>
   <tok>
    <orth>leży</orth>
    <lex disamb="1"><base>leżeć</base><ctag>fin:sg:ter:imperf</ctag></lex>
   </tok>
   <tok>
    <orth>Madagaskar</orth>
    <lex disamb="1"><base>Madagaskar</base><ctag>subst:sg:nom:m3</ctag></lex>
   </tok>
   <ns/>
   <tok>
    <orth>?</orth>
    <lex disamb="1"><base>?</base><ctag>interp</ctag></lex>
   </tok>
  </chunk>
  <chunk type="s">
   <tok>
    <orth>Gdzie</orth>
    <lex disamb="1"><base>gdzie</base><ctag>adv</ctag></lex>
   </tok>
   <tok>
    <orth>leży</orth>
    <lex disamb="1"><base>leżeć</base><ctag>fin:sg:ter:imperf</ctag></lex>
   </tok>
   <tok>
    <orth>Poznań</orth>
    <lex disamb="1"><base>Poznań</base><ctag>subst:sg:nom:m3</ctag></lex>
   </tok>
   <ns/>
   <tok>
    <orth>?</orth>
    <lex disamb="1"><base>?</base><ctag>interp</ctag></lex>
   </tok>
  </chunk>
  <chunk type="s">
   <tok>
    <orth>Gdzie</orth>
    <lex disamb="1"><base>gdzie</base><ctag>adv</ctag></lex>
   </tok>
   <tok>
    <orth>leży</orth>
    <lex disamb="1"><base>leżeć</base><ctag>fin:sg:ter:imperf</ctag></lex>
   </tok>
   <tok>
    <orth>Szczecin</orth>
    <lex disamb="1"><base>Szczecin</base><ctag>subst:sg:nom:m3</ctag></lex>
   </tok>
   <ns/>
   <tok>
    <orth>?</orth>
    <lex disamb="1"><base>?</base><ctag>interp</ctag></lex>
   </tok>
  </chunk>
  <chunk type="s">
   <tok>
    <orth>Na</orth>
    <lex disamb="1"><base>na</base><ctag>prep:loc</ctag></lex>
   </tok>
   <tok>
    <orth>jakiej</orth>
    <lex disamb="1"><base>jaki</base><ctag>adj:sg:loc:f:pos</ctag></lex>
   </tok>
   <tok>
    <orth>stronie</orth>
    <lex disamb="1"><base>strona</base><ctag>subst:sg:loc:f</ctag></lex>
   </tok>
   <tok>
    <orth>da</orth>
    <lex disamb="1"><base>dać</base><ctag>fin:sg:ter:perf</ctag></lex>
   </tok>
   <tok>
    <orth>się</orth>
    <lex disamb="1"><base>się</base><ctag>qub</ctag></lex>
   </tok>
   <tok>
    <orth>obejrzeć</orth>
    <lex disamb="1"><base>obejrzeć</base><ctag>inf:perf</ctag></lex>
   </tok>
   <tok>
    <orth>4</orth>
    <lex disamb="1"><base>4</base><ctag>num:pl:nom:m3:congr</ctag></lex>
   </tok>
   <ns/>
   <tok>
    <orth>-</orth>
    <lex disamb="1"><base>-</base><ctag>interp</ctag></lex>
   </tok>
   <ns/>
   <tok>
    <orth>ty</orth>
    <lex disamb="1"><base>ty</base><ctag>ppron12:sg:nom:m1:sec</ctag></lex>
   </tok>
   <tok>
    <orth>sezon</orth>
    <lex disamb="1"><base>sezon</base><ctag>subst:sg:nom:m3</ctag></lex>
   </tok>
   <tok>
    <orth>&quot;</orth>
    <lex disamb="1"><base>&quot;</base><ctag>interp</ctag></lex>
   </tok>
   <ns/>
   <tok>
    <orth>Pamiętnika</orth>
    <lex disamb="1"><base>pamiętnik</base><ctag>subst:sg:gen:m3</ctag></lex>
   </tok>
   <tok>
    <orth>Wampirów</orth>
    <lex disamb="1"><base>wampir</base><ctag>subst:pl:gen:m1</ctag></lex>
   </tok>
   <ns/>
   <tok>
    <orth>&quot;</orth>
    <lex disamb="1"><base>&quot;</base><ctag>interp</ctag></lex>
   </tok>
   <ns/>
   <tok>
    <orth>?</orth>
    <lex disamb="1"><base>?</base><ctag>interp</ctag></lex>
   </tok>
  </chunk>
  <chunk type="s">
   <tok>
    <orth>Gdzie</orth>
    <lex disamb="1"><base>gdzie</base><ctag>adv</ctag></lex>
   </tok>
   <tok>
    <orth>kupić</orth>
    <lex disamb="1"><base>kupić</base><ctag>inf:perf</ctag></lex>
   </tok>
   <tok>
    <orth>tanio</orth>
    <lex disamb="1"><base>tanio</base><ctag>adv:pos</ctag></lex>
   </tok>
   <tok>
    <orth>sukienkę</orth>
    <lex disamb="1"><base>sukienka</base><ctag>subst:sg:acc:f</ctag></lex>
   </tok>
   <tok>
    <orth>na</orth>
    <lex disamb="1"><base>na</base><ctag>prep:acc</ctag></lex>
   </tok>
   <tok>
    <orth>studniówkę</orth>
    <lex disamb="1"><base>studniówka</base><ctag>subst:sg:acc:f</ctag></lex>
   </tok>
   <ns/>
   <tok>
    <orth>?</orth>
    <lex disamb="1"><base>?</base><ctag>interp</ctag></lex>
   </tok>
  </chunk>
  <chunk type="s">
   <tok>
    <orth>Gdzie</orth>
    <lex disamb="1"><base>gdzie</base><ctag>adv</ctag></lex>
   </tok>
   <tok>
    <orth>mieszka</orth>
    <lex disamb="1"><base>mieszkać</base><ctag>fin:sg:ter:imperf</ctag></lex>
   </tok>
   <tok>
    <orth>yeti</orth>
    <lex disamb="1"><base>yeti</base><ctag>subst:sg:nom:m2</ctag></lex>
   </tok>
   <ns/>
   <tok>
    <orth>?</orth>
    <lex disamb="1"><base>?</base><ctag>interp</ctag></lex>
   </tok>
  </chunk>
  <chunk type="s">
   <tok>
    <orth>Gdzie</orth>
    <lex disamb="1"><base>gdzie</base><ctag>adv</ctag></lex>
   </tok>
   <tok>
    <orth>mieszka</orth>
    <lex disamb="1"><base>mieszkać</base><ctag>fin:sg:ter:imperf</ctag></lex>
   </tok>
   <tok>
    <orth>ksiądz</orth>
    <lex disamb="1"><base>ksiądz</base><ctag>subst:sg:nom:m1</ctag></lex>
   </tok>
   <tok>
    <orth>Natanek</orth>
    <lex disamb="1"><base>natanek</base><ctag>subst:sg:nom:m1</ctag></lex>
   </tok>
   <ns/>
   <tok>
    <orth>?</orth>
    <lex disamb="1"><base>?</base><ctag>interp</ctag></lex>
   </tok>
  </chunk>
  <chunk type="s">
   <tok>
    <orth>Gdzie</orth>
    <lex disamb="1"><base>gdzie</base><ctag>adv</ctag></lex>
   </tok>
   <tok>
    <orth>mieszka</orth>
    <lex disamb="1"><base>mieszkać</base><ctag>fin:sg:ter:imperf</ctag></lex>
   </tok>
   <tok>
    <orth>Tusk</orth>
    <lex disamb="1"><base>Tusk</base><ctag>subst:sg:nom:m1</ctag></lex>
   </tok>
   <ns/>
   <tok>
    <orth>?</orth>
    <lex disamb="1"><base>?</base><ctag>interp</ctag></lex>
   </tok>
  </chunk>
  <chunk type="s">
   <tok>
    <orth>Gdzie</orth>
    <lex disamb="1"><base>gdzie</base><ctag>adv</ctag></lex>
   </tok>
   <tok>
    <orth>mieszka</orth>
    <lex disamb="1"><base>mieszkać</base><ctag>fin:sg:ter:imperf</ctag></lex>
   </tok>
   <tok>
    <orth>Johnny</orth>
    <lex disamb="1"><base>johnny</base><ctag>subst:sg:nom:m1</ctag></lex>
   </tok>
   <tok>
    <orth>Depp</orth>
    <lex disamb="1"><base>depp</base><ctag>subst:sg:nom:m1</ctag></lex>
   </tok>
   <ns/>
   <tok>
    <orth>?</orth>
    <lex disamb="1"><base>?</base><ctag>interp</ctag></lex>
   </tok>
  </chunk>
  <chunk type="s">
   <tok>
    <orth>Gdzie</orth>
    <lex disamb="1"><base>gdzie</base><ctag>adv</ctag></lex>
   </tok>
   <tok>
    <orth>leży</orth>
    <lex disamb="1"><base>leżeć</base><ctag>fin:sg:ter:imperf</ctag></lex>
   </tok>
   <tok>
    <orth>rynek</orth>
    <lex disamb="1"><base>rynek</base><ctag>subst:sg:nom:m3</ctag></lex>
   </tok>
   <tok>
    <orth>w</orth>
    <lex disamb="1"><base>w</base><ctag>prep:loc:nwok</ctag></lex>
   </tok>
   <tok>
    <orth>Poznaniu</orth>
    <lex disamb="1"><base>Poznań</base><ctag>subst:sg:loc:m3</ctag></lex>
   </tok>
   <ns/>
   <tok>
    <orth>?</orth>
    <lex disamb="1"><base>?</base><ctag>interp</ctag></lex>
   </tok>
  </chunk>
  <chunk type="s">
   <tok>
    <orth>Gdzie</orth>
    <lex disamb="1"><base>gdzie</base><ctag>adv</ctag></lex>
   </tok>
   <tok>
    <orth>odbył</orth>
    <lex disamb="1"><base>odbyć</base><ctag>praet:sg:m3:perf</ctag></lex>
   </tok>
   <tok>
    <orth>się</orth>
    <lex disamb="1"><base>się</base><ctag>qub</ctag></lex>
   </tok>
   <tok>
    <orth>mecz</orth>
    <lex disamb="1"><base>mecz</base><ctag>subst:sg:nom:m3</ctag></lex>
   </tok>
   <tok>
    <orth>z</orth>
    <lex disamb="1"><base>z</base><ctag>prep:inst:nwok</ctag></lex>
   </tok>
   <tok>
    <orth>Grecją</orth>
    <lex disamb="1"><base>Grecja</base><ctag>subst:sg:inst:f</ctag></lex>
   </tok>
   <ns/>
   <tok>
    <orth>?</orth>
    <lex disamb="1"><base>?</base><ctag>interp</ctag></lex>
   </tok>
  </chunk>
  <chunk type="s">
   <tok>
    <orth>Gdzie</orth>
    <lex disamb="1"><base>gdzie</base><ctag>adv</ctag></lex>
   </tok>
   <tok>
    <orth>mogę</orth>
    <lex disamb="1"><base>móc</base><ctag>fin:sg:pri:imperf</ctag></lex>
   </tok>
   <tok>
    <orth>obejrzeć</orth>
    <lex disamb="1"><base>obejrzeć</base><ctag>inf:perf</ctag></lex>
   </tok>
   <tok>
    <orth>&quot;</orth>
    <lex disamb="1"><base>&quot;</base><ctag>interp</ctag></lex>
   </tok>
   <ns/>
   <tok>
    <orth>Bejbi</orth>
    <lex disamb="1"><base>bejbi</base><ctag>subst:sg:nom:m3</ctag></lex>
   </tok>
   <tok>
    <orth>Blues</orth>
    <lex disamb="1"><base>blues</base><ctag>subst:sg:nom:m3</ctag></lex>
   </tok>
   <ns/>
   <tok>
    <orth>&quot;</orth>
    <lex disamb="1"><base>&quot;</base><ctag>interp</ctag></lex>
   </tok>
   <ns/>
   <tok>
    <orth>?</orth>
    <lex disamb="1"><base>?</base><ctag>interp</ctag></lex>
   </tok>
  </chunk>
  <chunk type="s">
   <tok>
    <orth>Gdzie</orth>
    <lex disamb="1"><base>gdzie</base><ctag>adv</ctag></lex>
   </tok>
   <tok>
    <orth>można</orth>
    <lex disamb="1"><base>można</base><ctag>pred</ctag></lex>
   </tok>
   <tok>
    <orth>kupić</orth>
    <lex disamb="1"><base>kupić</base><ctag>inf:perf</ctag></lex>
   </tok>
   <tok>
    <orth>ćwieki</orth>
    <lex disamb="1"><base>ćwiek</base><ctag>subst:pl:acc:m3</ctag></lex>
   </tok>
   <ns/>
   <tok>
    <orth>?</orth>
    <lex disamb="1"><base>?</base><ctag>interp</ctag></lex>
   </tok>
  </chunk>
  <chunk type="s">
   <tok>
    <orth>Gdzie</orth>
    <lex disamb="1"><base>gdzie</base><ctag>adv</ctag></lex>
   </tok>
   <tok>
    <orth>mieszka</orth>
    <lex disamb="1"><base>mieszkać</base><ctag>fin:sg:ter:imperf</ctag></lex>
   </tok>
   <tok>
    <orth>Święty</orth>
    <lex disamb="1"><base>święty</base><ctag>adj:sg:nom:m1:pos</ctag></lex>
   </tok>
   <tok>
    <orth>Mikołaj</orth>
    <lex disamb="1"><base>Mikołaj</base><ctag>subst:sg:nom:m1</ctag></lex>
   </tok>
   <ns/>
   <tok>
    <orth>?</orth>
    <lex disamb="1"><base>?</base><ctag>interp</ctag></lex>
   </tok>
  </chunk>
  <chunk type="s">
   <tok>
    <orth>Gdzie</orth>
    <lex disamb="1"><base>gdzie</base><ctag>adv</ctag></lex>
   </tok>
   <tok>
    <orth>jest</orth>
    <lex disamb="1"><base>być</base><ctag>fin:sg:ter:imperf</ctag></lex>
   </tok>
   <tok>
    <orth>Ławica</orth>
    <lex disamb="1"><base>ławica</base><ctag>subst:sg:nom:f</ctag></lex>
   </tok>
   <ns/>
   <tok>
    <orth>?</orth>
    <lex disamb="1"><base>?</base><ctag>interp</ctag></lex>
   </tok>
  </chunk>
  <chunk type="s">
   <tok>
    <orth>Gdzie</orth>
    <lex disamb="1"><base>gdzie</base><ctag>adv</ctag></lex>
   </tok>
   <tok>
    <orth>leży</orth>
    <lex disamb="1"><base>leżeć</base><ctag>fin:sg:ter:imperf</ctag></lex>
   </tok>
   <tok>
    <orth>Nil</orth>
    <lex disamb="1"><base>Nil</base><ctag>subst:sg:nom:m1</ctag></lex>
   </tok>
   <ns/>
   <tok>
    <orth>?</orth>
    <lex disamb="1"><base>?</base><ctag>interp</ctag></lex>
   </tok>
  </chunk>
  <chunk type="s">
   <tok>
    <orth>Gdzie</orth>
    <lex disamb="1"><base>gdzie</base><ctag>adv</ctag></lex>
   </tok>
   <tok>
    <orth>leży</orth>
    <lex disamb="1"><base>leżeć</base><ctag>fin:sg:ter:imperf</ctag></lex>
   </tok>
   <tok>
    <orth>Paryż</orth>
    <lex disamb="1"><base>Paryż</base><ctag>subst:sg:nom:m3</ctag></lex>
   </tok>
   <ns/>
   <tok>
    <orth>?</orth>
    <lex disamb="1"><base>?</base><ctag>interp</ctag></lex>
   </tok>
  </chunk>
  <chunk type="s">
   <tok>
    <orth>Gdzie</orth>
    <lex disamb="1"><base>gdzie</base><ctag>adv</ctag></lex>
   </tok>
   <tok>
    <orth>jest</orth>
    <lex disamb="1"><base>być</base><ctag>fin:sg:ter:imperf</ctag></lex>
   </tok>
   <tok>
    <orth>Wrocław</orth>
    <lex disamb="1"><base>Wrocław</base><ctag>subst:sg:nom:m3</ctag></lex>
   </tok>
   <ns/>
   <tok>
    <orth>?</orth>
    <lex disamb="1"><base>?</base><ctag>interp</ctag></lex>
   </tok>
  </chunk>
  <chunk type="s">
   <tok>
    <orth>Gdzie</orth>
    <lex disamb="1"><base>gdzie</base><ctag>adv</ctag></lex>
   </tok>
   <tok>
    <orth>jest</orth>
    <lex disamb="1"><base>być</base><ctag>fin:sg:ter:imperf</ctag></lex>
   </tok>
   <tok>
    <orth>krzyż</orth>
    <lex disamb="1"><base>krzyż</base><ctag>subst:sg:nom:m3</ctag></lex>
   </tok>
   <ns/>
   <tok>
    <orth>?</orth>
    <lex disamb="1"><base>?</base><ctag>interp</ctag></lex>
   </tok>
  </chunk>
  <chunk type="s">
   <tok>
    <orth>Gdzie</orth>
    <lex disamb="1"><base>gdzie</base><ctag>adv</ctag></lex>
   </tok>
   <tok>
    <orth>jest</orth>
    <lex disamb="1"><base>być</base><ctag>fin:sg:ter:imperf</ctag></lex>
   </tok>
   <tok>
    <orth>lotnisko</orth>
    <lex disamb="1"><base>lotnisko</base><ctag>subst:sg:nom:n</ctag></lex>
   </tok>
   <tok>
    <orth>Ławica</orth>
    <lex disamb="1"><base>ławica</base><ctag>subst:sg:nom:f</ctag></lex>
   </tok>
   <ns/>
   <tok>
    <orth>?</orth>
    <lex disamb="1"><base>?</base><ctag>interp</ctag></lex>
   </tok>
  </chunk>
  <chunk type="s">
   <tok>
    <orth>Gdzie</orth>
    <lex disamb="1"><base>gdzie</base><ctag>adv</ctag></lex>
   </tok>
   <tok>
    <orth>jest</orth>
    <lex disamb="1"><base>być</base><ctag>fin:sg:ter:imperf</ctag></lex>
   </tok>
   <tok>
    <orth>Ogród</orth>
    <lex disamb="1"><base>ogród</base><ctag>subst:sg:nom:m3</ctag></lex>
   </tok>
   <tok>
    <orth>Japoński</orth>
    <lex disamb="1"><base>japoński</base><ctag>adj:sg:nom:m3:pos</ctag></lex>
   </tok>
   <ns/>
   <tok>
    <orth>?</orth>
    <lex disamb="1"><base>?</base><ctag>interp</ctag></lex>
   </tok>
  </chunk>
  <chunk type="s">
   <tok>
    <orth>Gdzie</orth>
    <lex disamb="1"><base>gdzie</base><ctag>adv</ctag></lex>
   </tok>
   <tok>
    <orth>leży</orth>
    <lex disamb="1"><base>leżeć</base><ctag>fin:sg:ter:imperf</ctag></lex>
   </tok>
   <tok>
    <orth>Poznań</orth>
    <lex disamb="1"><base>Poznań</base><ctag>subst:sg:nom:m3</ctag></lex>
   </tok>
   <ns/>
   <tok>
    <orth>?</orth>
    <lex disamb="1"><base>?</base><ctag>interp</ctag></lex>
   </tok>
  </chunk>
  <chunk type="s">
   <tok>
    <orth>Gdzie</orth>
    <lex disamb="1"><base>gdzie</base><ctag>adv</ctag></lex>
   </tok>
   <tok>
    <orth>leży</orth>
    <lex disamb="1"><base>leżeć</base><ctag>fin:sg:ter:imperf</ctag></lex>
   </tok>
   <tok>
    <orth>Warszawa</orth>
    <lex disamb="1"><base>Warszawa</base><ctag>subst:sg:nom:f</ctag></lex>
    <lex disamb="1"><base>warszawa</base><ctag>subst:sg:nom:f</ctag></lex>
   </tok>
   <ns/>
   <tok>
    <orth>?</orth>
    <lex disamb="1"><base>?</base><ctag>interp</ctag></lex>
   </tok>
  </chunk>
  <chunk type="s">
   <tok>
    <orth>Gdzie</orth>
    <lex disamb="1"><base>gdzie</base><ctag>adv</ctag></lex>
   </tok>
   <tok>
    <orth>aborcja</orth>
    <lex disamb="1"><base>aborcja</base><ctag>subst:sg:nom:f</ctag></lex>
   </tok>
   <tok>
    <orth>jest</orth>
    <lex disamb="1"><base>być</base><ctag>fin:sg:ter:imperf</ctag></lex>
   </tok>
   <tok>
    <orth>legalna</orth>
    <lex disamb="1"><base>legalny</base><ctag>adj:sg:nom:f:pos</ctag></lex>
   </tok>
   <ns/>
   <tok>
    <orth>?</orth>
    <lex disamb="1"><base>?</base><ctag>interp</ctag></lex>
   </tok>
  </chunk>
  <chunk type="s">
   <tok>
    <orth>Gdzie</orth>
    <lex disamb="1"><base>gdzie</base><ctag>adv</ctag></lex>
   </tok>
   <tok>
    <orth>jest</orth>
    <lex disamb="1"><base>być</base><ctag>fin:sg:ter:imperf</ctag></lex>
   </tok>
   <tok>
    <orth>Poznań</orth>
    <lex disamb="1"><base>Poznań</base><ctag>subst:sg:nom:m3</ctag></lex>
   </tok>
   <ns/>
   <tok>
    <orth>?</orth>
    <lex disamb="1"><base>?</base><ctag>interp</ctag></lex>
   </tok>
  </chunk>
  <chunk type="s">
   <tok>
    <orth>Gdzie</orth>
    <lex disamb="1"><base>gdzie</base><ctag>adv</ctag></lex>
   </tok>
   <tok>
    <orth>jest</orth>
    <lex disamb="1"><base>być</base><ctag>fin:sg:ter:imperf</ctag></lex>
   </tok>
   <tok>
    <orth>Opatówek</orth>
    <lex disamb="1"><base>opatówek</base><ctag>subst:sg:nom:m1</ctag></lex>
   </tok>
   <ns/>
   <tok>
    <orth>?</orth>
    <lex disamb="1"><base>?</base><ctag>interp</ctag></lex>
   </tok>
  </chunk>
  <chunk type="s">
   <tok>
    <orth>Gdzie</orth>
    <lex disamb="1"><base>gdzie</base><ctag>adv</ctag></lex>
   </tok>
   <tok>
    <orth>w</orth>
    <lex disamb="1"><base>w</base><ctag>prep:loc:nwok</ctag></lex>
   </tok>
   <tok>
    <orth>Krakowie</orth>
    <lex disamb="1"><base>Kraków</base><ctag>subst:sg:loc:m3</ctag></lex>
   </tok>
   <tok>
    <orth>znajduje</orth>
    <lex disamb="1"><base>znajdować</base><ctag>fin:sg:ter:imperf</ctag></lex>
    <lex disamb="1"><base>znajdywać</base><ctag>fin:sg:ter:imperf</ctag></lex>
   </tok>
   <tok>
    <orth>się</orth>
    <lex disamb="1"><base>się</base><ctag>qub</ctag></lex>
   </tok>
   <tok>
    <orth>sklep</orth>
    <lex disamb="1"><base>sklep</base><ctag>subst:sg:nom:m3</ctag></lex>
   </tok>
   <tok>
    <orth>New</orth>
    <lex disamb="1"><base>Newa</base><ctag>subst:pl:gen:f</ctag></lex>
   </tok>
   <tok>
    <orth>Yorker</orth>
    <lex disamb="1"><base>yorker</base><ctag>subst:sg:gen:f</ctag></lex>
   </tok>
   <ns/>
   <tok>
    <orth>?</orth>
    <lex disamb="1"><base>?</base><ctag>interp</ctag></lex>
   </tok>
  </chunk>
  <chunk type="s">
   <tok>
    <orth>Gdzie</orth>
    <lex disamb="1"><base>gdzie</base><ctag>adv</ctag></lex>
   </tok>
   <tok>
    <orth>wylądował</orth>
    <lex disamb="1"><base>wylądować</base><ctag>praet:sg:m3:perf</ctag></lex>
   </tok>
   <tok>
    <orth>samolot</orth>
    <lex disamb="1"><base>samolot</base><ctag>subst:sg:nom:m3</ctag></lex>
   </tok>
   <ns/>
   <tok>
    <orth>?</orth>
    <lex disamb="1"><base>?</base><ctag>interp</ctag></lex>
   </tok>
  </chunk>
  <chunk type="s">
   <tok>
    <orth>Gdzie</orth>
    <lex disamb="1"><base>gdzie</base><ctag>adv</ctag></lex>
   </tok>
   <tok>
    <orth>w</orth>
    <lex disamb="1"><base>w</base><ctag>prep:loc:nwok</ctag></lex>
   </tok>
   <tok>
    <orth>Poznaniu</orth>
    <lex disamb="1"><base>Poznań</base><ctag>subst:sg:loc:m3</ctag></lex>
   </tok>
   <tok>
    <orth>znajdę</orth>
    <lex disamb="1"><base>znajść</base><ctag>fin:sg:pri:perf</ctag></lex>
    <lex disamb="1"><base>znaleźć</base><ctag>fin:sg:pri:perf</ctag></lex>
   </tok>
   <tok>
    <orth>korty</orth>
    <lex disamb="1"><base>kort</base><ctag>subst:pl:acc:m3</ctag></lex>
   </tok>
   <tok>
    <orth>do</orth>
    <lex disamb="1"><base>do</base><ctag>prep:gen</ctag></lex>
   </tok>
   <tok>
    <orth>gry</orth>
    <lex disamb="1"><base>gra</base><ctag>subst:sg:gen:f</ctag></lex>
   </tok>
   <tok>
    <orth>w</orth>
    <lex disamb="1"><base>w</base><ctag>prep:acc:nwok</ctag></lex>
   </tok>
   <tok>
    <orth>tenisa</orth>
    <lex disamb="1"><base>tenis</base><ctag>subst:sg:acc:m2</ctag></lex>
   </tok>
   <ns/>
   <tok>
    <orth>?</orth>
    <lex disamb="1"><base>?</base><ctag>interp</ctag></lex>
   </tok>
  </chunk>
  <chunk type="s">
   <tok>
    <orth>Gdzie</orth>
    <lex disamb="1"><base>gdzie</base><ctag>adv</ctag></lex>
   </tok>
   <tok>
    <orth>w</orth>
    <lex disamb="1"><base>w</base><ctag>prep:loc:nwok</ctag></lex>
   </tok>
   <tok>
    <orth>Poznaniu</orth>
    <lex disamb="1"><base>Poznań</base><ctag>subst:sg:loc:m3</ctag></lex>
   </tok>
   <tok>
    <orth>znajdę</orth>
    <lex disamb="1"><base>znajść</base><ctag>fin:sg:pri:perf</ctag></lex>
    <lex disamb="1"><base>znaleźć</base><ctag>fin:sg:pri:perf</ctag></lex>
   </tok>
   <tok>
    <orth>korty</orth>
    <lex disamb="1"><base>kort</base><ctag>subst:pl:acc:m3</ctag></lex>
   </tok>
   <tok>
    <orth>do</orth>
    <lex disamb="1"><base>do</base><ctag>prep:gen</ctag></lex>
   </tok>
   <tok>
    <orth>gry</orth>
    <lex disamb="1"><base>gra</base><ctag>subst:sg:gen:f</ctag></lex>
   </tok>
   <tok>
    <orth>w</orth>
    <lex disamb="1"><base>w</base><ctag>prep:acc:nwok</ctag></lex>
   </tok>
   <tok>
    <orth>tenisa</orth>
    <lex disamb="1"><base>tenis</base><ctag>subst:sg:acc:m2</ctag></lex>
   </tok>
   <ns/>
   <tok>
    <orth>?</orth>
    <lex disamb="1"><base>?</base><ctag>interp</ctag></lex>
   </tok>
  </chunk>
  <chunk type="s">
   <tok>
    <orth>Gdzie</orth>
    <lex disamb="1"><base>gdzie</base><ctag>adv</ctag></lex>
   </tok>
   <tok>
    <orth>kupić</orth>
    <lex disamb="1"><base>kupić</base><ctag>inf:perf</ctag></lex>
   </tok>
   <tok>
    <orth>tani</orth>
    <lex disamb="1"><base>tani</base><ctag>adj:sg:acc:m3:pos</ctag></lex>
   </tok>
   <tok>
    <orth>duży</orth>
    <lex disamb="1"><base>duży</base><ctag>adj:sg:acc:m3:pos</ctag></lex>
   </tok>
   <tok>
    <orth>karton</orth>
    <lex disamb="1"><base>karton</base><ctag>subst:sg:acc:m3</ctag></lex>
   </tok>
   <tok>
    <orth>ozdobny</orth>
    <lex disamb="1"><base>ozdobny</base><ctag>adj:sg:acc:m3:pos</ctag></lex>
   </tok>
   <ns/>
   <tok>
    <orth>?</orth>
    <lex disamb="1"><base>?</base><ctag>interp</ctag></lex>
   </tok>
  </chunk>
  <chunk type="s">
   <tok>
    <orth>Gdzie</orth>
    <lex disamb="1"><base>gdzie</base><ctag>adv</ctag></lex>
   </tok>
   <tok>
    <orth>najłatwiej</orth>
    <lex disamb="1"><base>łatwie</base><ctag>adv:sup</ctag></lex>
    <lex disamb="1"><base>łatwo</base><ctag>adv:sup</ctag></lex>
   </tok>
   <tok>
    <orth>o</orth>
    <lex disamb="1"><base>o</base><ctag>prep:acc</ctag></lex>
   </tok>
   <tok>
    <orth>pracę</orth>
    <lex disamb="1"><base>praca</base><ctag>subst:sg:acc:f</ctag></lex>
   </tok>
   <ns/>
   <tok>
    <orth>?</orth>
    <lex disamb="1"><base>?</base><ctag>interp</ctag></lex>
   </tok>
  </chunk>
  <chunk type="s">
   <tok>
    <orth>Gdzie</orth>
    <lex disamb="1"><base>gdzie</base><ctag>adv</ctag></lex>
   </tok>
   <tok>
    <orth>znajdę</orth>
    <lex disamb="1"><base>znajść</base><ctag>fin:sg:pri:perf</ctag></lex>
    <lex disamb="1"><base>znaleźć</base><ctag>fin:sg:pri:perf</ctag></lex>
   </tok>
   <tok>
    <orth>informacje</orth>
    <lex disamb="1"><base>informacja</base><ctag>subst:pl:acc:f</ctag></lex>
   </tok>
   <tok>
    <orth>o</orth>
    <lex disamb="1"><base>o</base><ctag>prep:loc</ctag></lex>
   </tok>
   <tok>
    <orth>wysokości</orth>
    <lex disamb="1"><base>wysokość</base><ctag>subst:sg:loc:f</ctag></lex>
   </tok>
   <tok>
    <orth>długu</orth>
    <lex disamb="1"><base>dług</base><ctag>subst:sg:gen:m3</ctag></lex>
   </tok>
   <tok>
    <orth>publicznego</orth>
    <lex disamb="1"><base>publiczny</base><ctag>adj:sg:gen:m3:pos</ctag></lex>
   </tok>
   <ns/>
   <tok>
    <orth>?</orth>
    <lex disamb="1"><base>?</base><ctag>interp</ctag></lex>
   </tok>
  </chunk>
  <chunk type="s">
   <tok>
    <orth>Gdzie</orth>
    <lex disamb="1"><base>gdzie</base><ctag>adv</ctag></lex>
   </tok>
   <tok>
    <orth>znajdę</orth>
    <lex disamb="1"><base>znajść</base><ctag>fin:sg:pri:perf</ctag></lex>
    <lex disamb="1"><base>znaleźć</base><ctag>fin:sg:pri:perf</ctag></lex>
   </tok>
   <tok>
    <orth>informacje</orth>
    <lex disamb="1"><base>informacja</base><ctag>subst:pl:acc:f</ctag></lex>
   </tok>
   <tok>
    <orth>nt</orth>
    <lex disamb="1"><base>na temat</base><ctag>brev:pun</ctag></lex>
   </tok>
   <ns/>
   <tok>
    <orth>.</orth>
    <lex disamb="1"><base>.</base><ctag>interp</ctag></lex>
   </tok>
   <tok>
    <orth>poprawności</orth>
    <lex disamb="1"><base>poprawność</base><ctag>subst:sg:gen:f</ctag></lex>
   </tok>
   <tok>
    <orth>wykonania</orth>
    <lex disamb="1"><base>wykonać</base><ctag>ger:sg:gen:n:perf:aff</ctag></lex>
   </tok>
   <tok>
    <orth>budżetu</orth>
    <lex disamb="1"><base>budżet</base><ctag>subst:sg:gen:m3</ctag></lex>
   </tok>
   <ns/>
   <tok>
    <orth>?</orth>
    <lex disamb="1"><base>?</base><ctag>interp</ctag></lex>
   </tok>
  </chunk>
  <chunk type="s">
   <tok>
    <orth>Gdzie</orth>
    <lex disamb="1"><base>gdzie</base><ctag>adv</ctag></lex>
   </tok>
   <tok>
    <orth>najłatwiej</orth>
    <lex disamb="1"><base>łatwie</base><ctag>adv:sup</ctag></lex>
    <lex disamb="1"><base>łatwo</base><ctag>adv:sup</ctag></lex>
   </tok>
   <tok>
    <orth>o</orth>
    <lex disamb="1"><base>o</base><ctag>prep:acc</ctag></lex>
   </tok>
   <tok>
    <orth>pracę</orth>
    <lex disamb="1"><base>praca</base><ctag>subst:sg:acc:f</ctag></lex>
   </tok>
   <ns/>
   <tok>
    <orth>?</orth>
    <lex disamb="1"><base>?</base><ctag>interp</ctag></lex>
   </tok>
  </chunk>
  <chunk type="s">
   <tok>
    <orth>Gdzie</orth>
    <lex disamb="1"><base>gdzie</base><ctag>adv</ctag></lex>
   </tok>
   <tok>
    <orth>znajdę</orth>
    <lex disamb="1"><base>znajść</base><ctag>fin:sg:pri:perf</ctag></lex>
    <lex disamb="1"><base>znaleźć</base><ctag>fin:sg:pri:perf</ctag></lex>
   </tok>
   <tok>
    <orth>informacje</orth>
    <lex disamb="1"><base>informacja</base><ctag>subst:pl:acc:f</ctag></lex>
   </tok>
   <tok>
    <orth>o</orth>
    <lex disamb="1"><base>o</base><ctag>prep:loc</ctag></lex>
   </tok>
   <tok>
    <orth>wysokości</orth>
    <lex disamb="1"><base>wysokość</base><ctag>subst:sg:loc:f</ctag></lex>
   </tok>
   <tok>
    <orth>mienia</orth>
    <lex disamb="1"><base>mienie</base><ctag>subst:sg:gen:n</ctag></lex>
   </tok>
   <tok>
    <orth>Skarbu</orth>
    <lex disamb="1"><base>skarb</base><ctag>subst:sg:gen:m3</ctag></lex>
   </tok>
   <tok>
    <orth>Państwa</orth>
    <lex disamb="1"><base>państwo</base><ctag>subst:sg:gen:n</ctag></lex>
   </tok>
   <ns/>
   <tok>
    <orth>?</orth>
    <lex disamb="1"><base>?</base><ctag>interp</ctag></lex>
   </tok>
  </chunk>
  <chunk type="s">
   <tok>
    <orth>Gdzie</orth>
    <lex disamb="1"><base>gdzie</base><ctag>adv</ctag></lex>
   </tok>
   <tok>
    <orth>umarł</orth>
    <lex disamb="1"><base>umrzeć</base><ctag>praet:sg:m1:perf</ctag></lex>
   </tok>
   <tok>
    <orth>Rysiek</orth>
    <lex disamb="1"><base>Rysiek</base><ctag>subst:sg:nom:m1</ctag></lex>
   </tok>
   <ns/>
   <tok>
    <orth>?</orth>
    <lex disamb="1"><base>?</base><ctag>interp</ctag></lex>
   </tok>
  </chunk>
  <chunk type="s">
   <tok>
    <orth>Gdzie</orth>
    <lex disamb="1"><base>gdzie</base><ctag>adv</ctag></lex>
   </tok>
   <tok>
    <orth>położony</orth>
    <lex disamb="1"><base>położyć</base><ctag>ppas:sg:nom:m3:perf:aff</ctag></lex>
   </tok>
   <tok>
    <orth>jest</orth>
    <lex disamb="1"><base>być</base><ctag>fin:sg:ter:imperf</ctag></lex>
   </tok>
   <tok>
    <orth>Poznań</orth>
    <lex disamb="1"><base>Poznań</base><ctag>subst:sg:nom:m3</ctag></lex>
   </tok>
   <ns/>
   <tok>
    <orth>?</orth>
    <lex disamb="1"><base>?</base><ctag>interp</ctag></lex>
   </tok>
  </chunk>
  <chunk type="s">
   <tok>
    <orth>Gdzie</orth>
    <lex disamb="1"><base>gdzie</base><ctag>adv</ctag></lex>
   </tok>
   <tok>
    <orth>mieszka</orth>
    <lex disamb="1"><base>mieszkać</base><ctag>fin:sg:ter:imperf</ctag></lex>
   </tok>
   <tok>
    <orth>Kulczyk</orth>
    <lex disamb="1"><base>kulczyk</base><ctag>subst:sg:nom:m2</ctag></lex>
   </tok>
   <ns/>
   <tok>
    <orth>?</orth>
    <lex disamb="1"><base>?</base><ctag>interp</ctag></lex>
   </tok>
  </chunk>
  <chunk type="s">
   <tok>
    <orth>Gdzie</orth>
    <lex disamb="1"><base>gdzie</base><ctag>adv</ctag></lex>
   </tok>
   <tok>
    <orth>pochowano</orth>
    <lex disamb="1"><base>pochować</base><ctag>imps:perf</ctag></lex>
   </tok>
   <tok>
    <orth>Hankę</orth>
    <lex disamb="1"><base>Hanka</base><ctag>subst:sg:acc:f</ctag></lex>
   </tok>
   <tok>
    <orth>Mostowiak</orth>
    <lex disamb="1"><base>mostowiak</base><ctag>subst:sg:acc:f</ctag></lex>
   </tok>
   <ns/>
   <tok>
    <orth>?</orth>
    <lex disamb="1"><base>?</base><ctag>interp</ctag></lex>
   </tok>
  </chunk>
  <chunk type="s">
   <tok>
    <orth>Gdzie</orth>
    <lex disamb="1"><base>gdzie</base><ctag>adv</ctag></lex>
   </tok>
   <tok>
    <orth>odbył</orth>
    <lex disamb="1"><base>odbyć</base><ctag>praet:sg:m3:perf</ctag></lex>
   </tok>
   <tok>
    <orth>się</orth>
    <lex disamb="1"><base>się</base><ctag>qub</ctag></lex>
   </tok>
   <tok>
    <orth>Enter</orth>
    <lex disamb="1"><base>enter</base><ctag>subst:sg:nom:m3</ctag></lex>
   </tok>
   <tok>
    <orth>Festival</orth>
    <lex disamb="1"><base>festival</base><ctag>subst:sg:nom:m3</ctag></lex>
   </tok>
   <ns/>
   <tok>
    <orth>?</orth>
    <lex disamb="1"><base>?</base><ctag>interp</ctag></lex>
   </tok>
  </chunk>
  <chunk type="s">
   <tok>
    <orth>Gdzie</orth>
    <lex disamb="1"><base>gdzie</base><ctag>adv</ctag></lex>
   </tok>
   <tok>
    <orth>można</orth>
    <lex disamb="1"><base>można</base><ctag>pred</ctag></lex>
   </tok>
   <tok>
    <orth>uprawiać</orth>
    <lex disamb="1"><base>uprawiać</base><ctag>inf:imperf</ctag></lex>
   </tok>
   <tok>
    <orth>seks</orth>
    <lex disamb="1"><base>seks</base><ctag>subst:sg:acc:m3</ctag></lex>
   </tok>
   <ns/>
   <tok>
    <orth>?</orth>
    <lex disamb="1"><base>?</base><ctag>interp</ctag></lex>
   </tok>
  </chunk>
  <chunk type="s">
   <tok>
    <orth>Gdzie</orth>
    <lex disamb="1"><base>gdzie</base><ctag>adv</ctag></lex>
   </tok>
   <tok>
    <orth>mieszka</orth>
    <lex disamb="1"><base>mieszkać</base><ctag>fin:sg:ter:imperf</ctag></lex>
   </tok>
   <tok>
    <orth>Doda</orth>
    <lex disamb="1"><base>dodać</base><ctag>fin:sg:ter:perf</ctag></lex>
   </tok>
   <ns/>
   <tok>
    <orth>?</orth>
    <lex disamb="1"><base>?</base><ctag>interp</ctag></lex>
   </tok>
  </chunk>
 </chunk>
</chunkList>
</cesAna>
